Workbook
Name AfA_Art: Parameter!$B$19
Name AfA_Tabelle: AfA!$A$16:$F$46
Name AFABasis: Parameter!$B$20
Name Annuität_Förderkredit: Parameter!$I$66
Name Annuität_Kredit_1_p.a.: Parameter!$B$66
Name Annuität_Kredit_2_p.a.: Parameter!$B$75
Name Anschlusskredit: Parameter!$B$70
Name Anzahl_Tilgungszuschüsse: Parameter!$I$62
Name AuszahungKredit1: Parameter!$B$63
Name Baukostensteigerung_p.a: Parameter!$B$25
Name BeginnFolgeKredit: Parameter!$D$69
Name Deg5Lin2: AfA!$C$15
Name Deg5Lin3: AfA!$B$15
Name Disagio: Parameter!$B$62
Name Disagio_in_Prozent: Parameter!$B$61
Name Eigenkapital: Parameter!$B$51
Name Finanzbedarf: Parameter!$B$53
Name FinZeitraum: Parameter!$B$54
Name FittingUp: Parameter!$B$14
Name Förderkredit: Parameter!$I$59
Name Förderzeit: Parameter!$I$57
Name Förderzins: Parameter!$I$64
Name Gebäude: Parameter!$B$6
Name Grenzsteuersatz: Parameter!$B$47
Name Grundbuchamt: Parameter!$B$10
Name Grunderwerbsteuer: Parameter!$B$8
Name Grundstück: Parameter!$B$5
Name Instanhaltungskosten_am_Anfang: Parameter!$B$15
Name Investment: Parameter!$B$52
Name Kreditbedarf: Parameter!$B$59
Name Kreditzins1: Parameter!$B$64
Name Kreditzins2: Parameter!$B$71
Name LaufzeitKredit1: Parameter!$B$57
Name LaufzeitKredit2: Parameter!$D$69
Name Lebensdauer: Parameter!$B$18
Name Linear2: AfA!$E$15
Name Linear3: AfA!$D$15
Name LinearX: AfA!$F$15
Name Maklergebühren: Parameter!$B$9
Name Mietpreissteigerung_p.a.: Parameter!$B$44
Name Notargebühren: Parameter!$B$11
Name RBWnach6Jahren: 'Cash & Assets'!$AB$13
Name Restlaufzeit: Parameter!$B$73
Name Start: Parameter!$E$3
Name Startjahr: Parameter!$B$3
Name Tilgungszuschuss: Parameter!$I$61
Name Unterhaltskosten_p.a.: Parameter!$B$33
Name Unterhaltskostensteigerung: Parameter!$B$34
Name Verkaufsjahr: Parameter!#REF!
Name Wertverlust_des_Gebäudes_p.a.: Parameter!$B$23
Name Wertzuwachst_des_Grundstücks_p.a.: Parameter!$B$24

Sheet Hinweise
A1: Was bringt eine vermietete Immobilie? | F1: Version | G1: V 5.0 | H1: vom | I1: 45989
A2: Wie muss ein Immobilien-Investor mit Förderkredit rechnen?
A3: Modellrechnung
A4: Nach-Steuer-Belastung einer vermieteten, kredit-finanzierten Immobilie!
A6: Die Dateneingabe der Paramater erfolgt durch
A7: Übertippen der Eingaben in den gelben Feldern
A8: in dem Arbeitsblatt "Parameter"
A10: Warnung:
A12: Diese Excel-Kalkulation wird kostenfrei ohne Haftungs- und Gewährleistungsansprüche überlassen.
A13: Dieses Tool ersetzt keine fundierte Rechts-, Steuer- oder Finanzberatung.
A14: Dieses Tool stellt ein Nebenprodukt meiner Tätigkeit in meinen Private Office dar und wurde nicht entwickelt, um es als Produkt zu vermarkten.
A15: Es wird keine Gewährleistung und Haftung für die Richtigkeit der Kalkulationen übernommen.
A16: Es handelt sich um eine Modellrechnung (Szenario-Rechnung) und keine Prognose. Das bedeutet, da Ergebnis zeigt lediglich,
... A66: Die degressive AfA (Absetzung für Abnutzung) im Überblick
A67: Quelle: | B67: https://www.bmwsb.bund.de/SharedDocs/kurzmeldungen/Webs/BMWSB/DE/2024/03/degressive-afa.html
A68: Die degressive Abschreibung gilt ausschließlich für neu gebaute bzw. im Jahr der Fertigstellung erworbene Wohngebäude und Wohnungen.
A69: Im ersten Jahr können fünf Prozent der Investitionskosten steuerlich geltend gemacht werden. In den folgenden Jahren können jeweils fünf Prozent des Restwertes steuerlich geltend gemacht werden.
A70: Ein Wechsel zur linearen AfA ist möglich.
A71: Der Baubeginn des Wohngebäudes muss zwischen dem 1. Oktober 2023 und dem 30. September 2029 (6-Jahres Zeitraum) liegen.
A72: * Höhe der degressiven AfA: 5 % pro Jahr
A73: * Dauer der degressiven Abschreibung: 6 Jahre
A74: * Wechsel zur linearen AfA lohnt sich ab dem 7. Jahr oder wenn die lineare AfA (3 %) höher ist als die degressive AfA
A75: Erstmals ist nicht der Bauantrag entscheidendes Kriterium für die Gewährung der degressiven AfA, sondern der angezeigte Baubeginn. So wollen wir auch die Umsetzung von Projekten anreizen, die zwar schon geplant, aber aus unterschiedlichen Gründen – z. B. Probleme bei der Finanzierung – noch nicht begonnen wurden. Damit soll auch der Bauüberhang von mehr als 800.000 genehmigten Wohnungen abgebaut werden.
A76: Beim Erwerb einer Immobilie muss der Vertrag zwischen dem 1. Oktober 2023 und dem 30. September 2029 rechtswirksam geschlossen werden. Die Immobilie muss bis zum Ende des Jahres der Fertigstellung erworben werden.
A77: Die degressive AfA kann zudem mit der Sonderabschreibung für den Mietwohnungsneubau kombiniert werden. Begünstigt werden dabei Neubauten, mit dem energetischen Gebäudestandard EH40/QNG, die eine Baukostenobergrenze von 5.200 Euro pro m² einhalten.
A78: Die Bedingungen für die genannte Sonderabschreibung für den Mietwohnungsneubau wurden mit dem Wachstumschancengesetz nochmal verbessert: Der Anwendungszeitraum für Neufälle wurde bis Ende September 2029 verlängert, die Baukostenobergrenze von 4.800 Euro pro m² auf 5.200 Euro pro m² und die begünstigten Herstellungs-/Anschaffungskosten von 2.500 Euro pro m² auf 4.000 Euro pro m² erhöht.
A79: siehe auch: | B79: https://ivd.net/bundesverband/steuerliche-vorteile-im-wohnungsbau-degressive-afa-sonderabschreibung
A81: Beispielrechnung
A82: Bei 400.000 Euro Investitionskosten kann der Investor im ersten Jahr 20.000 Euro (5 Prozent von 400.000 Euro) steuerlich abschreiben, im zweiten Jahr sind dann 19.000 Euro abschrei-bungsfähig (400.000 Euro abzüglich der 20.000 Euro vom ersten Jahr = 380.000 Euro Restwert). Innerhalb von sechs Jahren nach Fertigstellung/Erwerb der Immobilie kann der Investor so rund 106.000 Euro steuerlich geltend machen (d.h. auf diesen Betrag müssen keine Steuern entrichtet werden).
A85: Lineare AfA: Drei statt zwei Prozent ab dem 1.1.2023
A86: Quelle: | B86: https://www.haufe.de/immobilien/wirtschaft-politik/abschreibung-beim-mietwohnungsbau_84342_572146.html
A87: § 7 Abs. 4 Satz 1 Nr. 2 EStG: Die lineare Absetzung für Abnutzung (lineare AfA) wurde zum 1.1.2023 von zwei auf drei Prozent pro Jahr angehoben. Darauf hatten sich die Ampel-Parteien bereits im Koalitionsvertrag verständigt.
A88: Die aus dem Ansatz des höheren pauschalen AfA-Satzes resultierende kürzere Abschreibungsdauer von 33 Jahren hat aber keinen Einfluss auf die Beurteilung der tatsächlichen Nutzungsdauer von Wohngebäuden. Diese wird regelmäßig auch mehr als 50 Jahre betragen.
A89: Die Maßnahme gilt für ab dem 1.1.2023 fertiggestellte Wohngebäude (Regierungsentwurf: 30.6.2023).
A91: siehe auch: | B91: https://prozentguru.de/gebaeude-afa-3-prozent/
A92: siehe auch: | B92: https://www.baumeister-online.de/nachricht/bundesrat-stimmt-wachstumschancengesetz-zu-degressive-afa-kommt/
A98: Die jährliche (Anfangs-)Tilgung
A100: Die jährliche (Anfangs-)Tilgung kann in diesem Modell nicht explizit als Parameter eingeben werden.
A101: Die Höhe der Tilgung p.a. in Prozent hängt ab von der gewählten Finanzierungsdauer (Finanzierungszeitraum, siehe Blatt „Parameter“ Zelle B54).
A102: Die Tilgung in % p.a. findet sich in der Spalte K des Blatts „Cash & Assets“
A111: Wählt man/frau z. B. einen Finanzierungszeitraum von 48 Jahren, dann sinkt u.U. die Tilgung p.a. auf ca. ein Prozent (siehe Abb.).
A112: Bei einen Finanzierungszeitraum von 32 Jahren ergibt sich eine Tilgung von ca. zwei Prozent p.a.
A113: Wenn man/frau einen besonders langen Finanzierungszeitraum wählt, verringert sich die anfängliche jährliche Tilgung in Prozent. Dafür zahlt dann man/frau entsprechend länger.
A115: Den Zusammenhang zwischen Tilgung p.a. und Tilgungsdauer verdeutlicht nachfolgende Tabelle.
A117: Tilgungsdauer in Jahren | G117: Annuität =
A118: bei einer Tilgung von x % p.a. | G118: Zins p.a. + Tilgung p.a.
A119: und Zinsen von y % p.a.
B120: Zins p.a.
A121: Tilgung p.a. | B121: 0.01 | C121: 0.02 | D121: 0.03 | E121: 0.04 | F121: 0.05 | G121: 0.06 | H121: 0.07 | I121: 0.08
A122: 0.01 | B122: 69.3 | C122: 55 | D122: 46.3 | E122: 40.3 | F122: 35.9 | G122: 32.5 | H122: 29.8 | I122: 27.6
A123: 0.02 | B123: 40.6 | C123: 34.7 | D123: 30.6 | E123: 27.5 | F123: 25.1 | G123: 23.2 | H123: 21.5 | I123: 20.2
A124: 0.03 | B124: 28.8 | C124: 25.6 | D124: 23.1 | E124: 21.2 | F124: 19.7 | G124: 18.4 | H124: 17.2 | I124: 16.3
A125: 0.04 | B125: 22.3 | C125: 20.3 | D125: 18.7 | E125: 17.4 | F125: 16.3 | G125: 15.3 | H125: 14.5 | I125: 13.8
A126: 0.05 | B126: 18.2 | C126: 16.8 | D126: 15.7 | E126: 14.7 | F126: 13.9 | G126: 13.2 | H126: 12.5 | I126: 12
A127: 0.06 | B127: 15.4 | C127: 14.4 | D127: 13.5 | E127: 12.8 | F127: 12.1 | G127: 11.6 | H127: 11.1 | I127: 10.6
A128: 0.07 | B128: 13.4 | C128: 12.6 | D128: 11.9 | E128: 11.3 | F128: 10.8 | G128: 10.3 | H128: 9.9 | I128: 9.6
A129: 0.08 | B129: 11.8 | C129: 11.2 | D129: 10.6 | E129: 10.2 | F129: 9.7 | G129: 9.4 | H129: 9 | I129: 8.7
A130: 0.09 | B130: 10.5 | C130: 10 | D130: 9.6 | E130: 9.2 | F130: 8.9 | G130: 8.5 | H130: 8.2 | I130: 8
A131: 0.1 | B131: 9.5 | C131: 9.1 | D131: 8.8 | E131: 8.4 | F131: 8.1 | G131: 7.9 | H131: 7.6 | I131: 7.4
A133: Man beachte: Annuität (Höhe der regelmäßigen Zahlung für Zins und Tilgung) bleibt während der gesamten Laufzeit gleich!
A139: Info zur Zinsentwicklung: | B139: https://index.fmh.de/fmh-index/ueberblick/
A142: Warnung
A143: Bevor Sie den Rechner benutzen, sollten Sie beachten: Das Programm kann Ihnen eine wichtige Orientierung über den möglichen Verlauf Ihrer Investition und die Rentabilität einer Immobilie geben – aber keine Sicherheit. In die Ergeb­nisse fließen zwangs­läufig unsichere Annahmen vor allem über die Miet­entwick­lung und den künftigen Verkaufs­erlös der Immobilie ein. Schon kleinere Änderungen bei den Prognose­annahmen können die Ergeb­nisse erheblich verändern. Rechnen Sie deshalb immer mehrere Szenarien durch und gehen Sie eher von vorsichtigen Annahmen aus. Rechnet sich die Immobilie nur bei hohen Miet­steigerungen in der Zukunft, handelt es sich letzt­lich um eine spekulative Anlage mit hohem Risiko.
A154: Gewährleistung und Restriktionen
A155: Keine Gewähr für die Richtigkeit der Angaben. Dieses Tool ersetzt keine fundierte Rechts-, Steuer- oder Finanzberatung.
A156: Dieses Tool stellt ein Nebenprodukt meiner Tätigkeit in meinem Private Office dar und wurde nicht entwickelt, um es kommerziell zu vermarkten.
A157: Es wird keine Gewährleistung und Haftung für die Richtigkeit der Kalkulationen übernommen.
A158: Es handelt sich um eine Modellrechnung (Szenario-Rechnung) und keine Prognose.
A159: Das bedeutet, das Ergebnis zeigt lediglich, wie die Belastung(en) aussehen könnte(n), wenn alle die gesetzten Annahmen und Parameter so eintreffen würden.

Sheet Parameter
A1: Dateneingabe: | B1: in den Gelben Parameter-Feldern | F1: Objekt und Größe | M1: Grunderwerbsteuer nach Bundesländern
A2: Parameter für vermietes Objekt | B2: Version vom | C2: =Hinweise!I1 -> 45989 | F2: Adresse | G2: Musterstraße 123, 45678 Irgendwo | M2: Baden-Württemberg | N2: 0.05
A3: Kauf am: | B3: 46023 | C3: = Start bzw.Jahr | E3: 0 | F3: Nutz- u.Wohnfläche | G3: =B7 -> 144 | H3: Grundstück | I3: 500 | M3: Bayern | N3: 0.035
A4: Kaufpreis (Grundstück & Gebäude) | B4: =Grundstück+Gebäude -> 1000000 | C4: =IF(C5+C6<>1," Check Anteile!","") | M4: Berlin | N4: 0.06
A5: davon für Grundstück | B5: 200000 | C5: =Grundstück/B4 -> 0.2 | D5: Grundstücksanteil am Kaufpreis | H5: =Grundstück/I3 -> 400 | I5: pro m² Gund | J5: vgl. Bodenrichtwert | M5: Brandenburg | N5: 0.065
A6: davon für Gebäude | B6: 800000 | C6: =Gebäude/B4 -> 0.8 | D6: Gebäudeanteil am Kaufpreis; dient zum Verrechnen der anteiligen Erwerbsnebenkosten | M6: Bremen | N6: 0.05
A7: Anzahl Quadratmeter Nutz- u. Wohnfläche | B7: 144 | C7: =B4/B7 -> 6944.4444 | D7: Preis für Nutz- u. Wohnraum pro m² (mit Grundst. gerechnet) | M7: Hamburg | N7: 0.045
A8: Grunderwerbsteuer | B8: =(Gebäude+Grundstück)*C8 -> 50000 | C8: 0.05 | D8: auf Kaufpreis (=Grund & Gebäude) | M8: Hessen | N8: 0.06
A9: Maklergebühren | B9: =(Gebäude+Grundstück)*C9 -> 35700 | C9: =1.19*3% -> 0.0357 | D9: auf Kaufpreis (unterschiedlich je Bundesland) | M9: Mecklenburg-Vorpommern | N9: 0.05
A10: Grundbuch Amt | B10: =(Gebäude+Grundstück)*C10 -> 5000 | C10: 0.005 | D10: geschätzt, kann variieren | M10: Niedersachsen | N10: 0.05
A11: Notargebühren | B11: =(Gebäude+Grundstück)*C11 -> 15000 | C11: 0.015 | D11: geschätzt, muss beim Notar erfragt werden! | M11: Nordrhein-Westfalen | N11: 0.065
A12: Gründung Immobilien Gesellschaft | B12: 0 | M12: Rheinland-Pfalz | N12: 0.05
A13: Erwerbsnebenkosten (ENK) | B13: =SUM(B8:B12) -> 105700 | C13: =SUM(C8:C11) -> 0.1057 | M13: Saarland | N13: 0.065
A14: Fitting up (erhöht den Gebäudewert) | B14: 40000 | C14: Das Fitting up erhöht den Gebäudewert und wird über die Abschreibungsdauer abgeschrieben. | M14: Sachsen | N14: 0.035
A15: Instandsetzung am Anfang | B15: 2500 | C15: Die Instandsetzungskosten (z.B. Reparaturen) werden im Jahr des Kaufs steuerlich angesetzt! | M15: Sachsen-Anhalt | N15: 0.05
A16: Gesamtkosten | B16: =Instanhaltungskosten_am_Anfang+FittingUp+B4+B13 -> 1148200 | C16: Investitionsvolumen (ohne Disagio) | M16: Schleswig-Holstein | N16: 0.065
M17: Thüringen | N17: 0.065
A18: Gebäude-Abschreibung über | B18: 50 | C18: Jahre | D18: der Restnutzungsdauer
A19: AfA: Linear oder Degressiv-Linear? | B19: Linear 2% | C19: <- Klicke auf Zelle & Wähle mit Lasche!
A20: AfA Basis (Gebäudewert + anteilige ENK) | B20: =Gebäude+FittingUp+B13*C6 -> 924560 | C20: = Gebäudewert bei Kauf + Fittiing up + anteilige Erwerbsnebenkosten (ENK)
A22: Asset-Wertentwicklung
A23: Wertverlust des Gebäudes p.a. | B23: 0.01 | C23: Altersabschlag = Parameter für Verkaufswertermittlung
A24: Wertzuwachs des Grundstücks p.a. | B24: 0.01 | C24: Parameter für Verkaufswertermittlung | L24: Maklerprovision | M24: in % | N24: Stand 2020
A25: Preissteigerung von Baukosten p.a. | B25: 0.015 | C25: Parameter für Verkaufswertermittlung | L25: Deutschland | M25: 0.04375 | N25: Durchschn.
A27: Sondertilgungen und Sonderabschreibungen sind in der Tabelle "Cash & Assets" manuell einzugeben! | L27: Baden-Wuerttemberg | M27: 0.0357
L28: Bayern | M28: 0.0357
A29: An Mieter umlegbare / weiterbelastare Kosten! n/a | C29: Bleiben außen vor, da diese Kosten nicht selbst sondern vom Mieter getragen werden! | L29: Brandenburg | M29: 0.0714 | O29: Keine Gewähr für die Richtigkeit der Angaben. Dieses Tool ersetzt keine fundierte Rechts-, Steuer- oder Finanzberatung.
A30: Hausverwaltung, Hausmeister, etc. p.a. | B30: 480 | C30: Nicht an Mieter weiterbelastare Kosten! | L30: Hessen | M30: 0.0595
A31: lfd. Reparturen und Instandhaltung p.a. | B31: =B7*C31 -> 864 | C31: 6 | D31: / m² p.a. geschätzt ! Bitte anpassen! | L31: Mecklenburg-Vorpommern | M31: 0.0357
A32: Instandhaltungsrücklage p.a | B32: =B7*C32 -> 720 | C32: 5 | D32: / m² p.a. geschätzt ! Bitte anpassen! | L32: Niedersachsen | M32: 0.05 | N32: 3,57 bis 5,95
A33: Bewirtschtungs-/Unterhaltskosten incl. Instandhaltungsrücklage p.a. | B33: =SUM(B30:B32) -> 2064 | C33: =Unterhaltskosten_p.a./B7 -> 14.333333 | D33: / m² p.a. | L33: Nordrhein-Westfalen | M33: 0.0357
A34: Unterhaltskostensteigerung p.a. | B34: 0.0125 | C34: geschätzt bitte anpassen! | L34: Rheinland-Pfalz | M34: 0.0357
L35: Saarland | M35: 0.0357 | P35: Achtung:
L36: Sachsen-Anhalt | M36: 0.0357 | P36: Änderung der Maklerprovisionen in 2021 erwartet!
A37: Miete p.m. | B37: 2000 | C37: =B37/B7 -> 13.888889 | D37: Mietpreis für Wohn-Nutzfläche pro m² | L37: Sachsen | M37: 0.0357
A38: Miete p.a. | B38: =B37*12 -> 24000 | L38: Schleswig-Holstein | M38: 0.0357
A39: Durchschn. Mietausfalls-/Leerstandsrisiko | B39: 0.02 | C39: p.a. | D39: wird als Mietminderung in Kalkulation berücksichtigt! | L39: Thüringen | M39: 0.0357
A40: nachhaltige durchschn. Miete p.a. | B40: =B38*(1-B39) -> 23520 | C40: unter Berücksichtigung des Mietausfallsrisikos und der Instandhaltung | L40: Berlin | M40: 0.0714
A41: nachh. Mietrendite p.a. | B41: =B40/B16 -> 0.020484236 | C41: Miete p.a. in Prozent des Investitionsvolumens | L41: Bremen | M41: 0.0595
A42: Investition als Vielfaches der Jahresmiete | B42: =B16/B40 -> 48.818027 | C42: =" Investitionsvolumen entspricht dem "&ROUND(B42,1)&" fachen einer nachh. Jahresmiete" -> Investitionsvolumen entspricht dem 48,8 fachen einer nachh. Jahresmiete | L42: Hamburg | M42: 0.0312
A43: 1. Miete am: | B43: =B3 -> 46023 | C43: = Jahr | D43: 1
A44: Mietpreissteigerung p.a. | B44: 0.0125 | C44: Annahme, bitte anpassen!
A47: Angenommener Grenz-Steuersatz | B47: 0.42 | C47: Hängt ab von Einkommen/-sentwicklung! Kann über Betrachtungszeitraum schwanken! Fragen Sie dazu ihren Steuer- oder Finanzberater.
A50: Finanzierung über Annuitätendarlehn einer Hausbank | F50: Modellrechnung unterstellt zwei aufeinanderfolgenden Hausbankkredite sowie
A51: Eigenkapital | B51: 100000 | F51: einen "Förderkredit" parallel zum 1. Hausbankkredit am Anfang des Projektes!
A52: Gesamtinvestion | B52: =B16 -> 1148200
A53: Finanzbedarf | B53: =B52-B51 -> 1048200 | C53: Investitionsvolumen (ohne Disagio) | F53: Finanzierung mit "Förderkredit" | K53: Statt eines Förderkredits kann dieser Eingabe-Bereich für einen 2.
A54: Finanzierungszeitraum | B54: 25 | C54: Jahre | D54: =IF(Lebensdauer<FinZeitraum,"ACHTUNG: Finanzierungszeitraum sollte die Restnutzungsdauer nicht übersteigen!","") | F54: Parallel zum ersten Kredit ab dem 1. Jahr | K54: Bankkredit mit unterschiedlichen Konditionen und Laufzeit genutzt
A55: Anfängl. Jähliche Tilgung in % | B55: ='Cash & Assets'!T8 -> 0.033461893 | F55: Förderkredit von: | I55: Name der Bank | K55: werden, der ebenfalls bei Beginn des Projekts startet.
A56: 1. Kredit | B56: Anfangskredit | F56: Zugesagte Höhe der Mittel | I56: 50000 | K56: Zum Ende der Kreditlaufzeit ist dann dieser Kredit komplett getilgt (NULL)! Es ist kein Folgekredit möglich!
A57: Zinsbindung in Jahren | B57: 10 | F57: Finanzierungszeitraum in Jahren | I57: 8 | K57: <= Der Förderkredit muss dann komplett getilgt sein!
A58: Zinsbindung endet im Jahr | B58: =YEAR(Startjahr)+I57 -> 2034 | D58: ACHTUNG | F58: Kredit endet im Jahr | I58: =IFERROR(YEAR(Startjahr)+Förderzeit,"") -> 2034 | K58: <= Model sieht kein Folge(Förder)kredit vor!
A59: Kreditbedarf bei Hausbank | B59: =Finanzbedarf-Förderkredit -> 998200 | C59: Kreditbedarf bei Hausbank = Finanzbedarf - Förderkredit | F59: Förderkredithöhe | I59: =I56 -> 50000 | K59: Falls kein Förderkredit genutzt wird,
A60: Auszahlungkurs in Prozent | B60: =1-B61 -> 1 | F60: Auszahlungkurs in Prozent | I60: 1 | K60: ist die Höhe der Fördermittel auf Null zu setzen!
A61: Disagio in Prozent | B61: 0 | F61: Tilgungszuschuss p.a. | I61: 1500 | K61: <- Betrag p.a. aus dem Förderkreditvetrag
A62: Diasagio-Betrag: | B62: =AuszahungKredit1-Kreditbedarf -> 0 | F62: Anzahl Tilgungszuschüsse (Jahre) | I62: 5 | K62: <- Anzahl aus dem Förderkreditvetrag
A63: Auszahlungsbetrag: | B63: =B59/B60 -> 998200 | F63: Summe Tilgungszuschüsse | I63: =IF(AND(ISNUMBER(Tilgungszuschuss),ISNUMBER(Anzahl_Tilgungszuschüsse)),I62*I61,0) -> 7500
A64: Nominalzins p.a. | B64: 0.0285 | F64: Nominalzins p.a. | I64: 0.0285 | K64: <- Zins aus dem Förderkreditvertrag
A65: entspricht Effektivzins ca. | B65: =EFFECT(Kreditzins1,12) -> 0.028875244 | C65: bei monatl. Tilgung | F65: entspricht Effektivzins ca. | I65: =EFFECT(Förderzins,12) -> 0.028875244 | K65: bei monatl. Tilgung
A66: Annuität 1. Kredit p.a. | B66: =-PMT(Kreditzins1,FinZeitraum,AuszahungKredit1,0,0) -> 56370.637 | F66: Annuität Förderkredit p.a. | I66: =IF(ISNUMBER(Förderzeit),-PMT(Förderzins,Förderzeit,Förderkredit,0,0),0) -> 7077.8193 | K66: <- Annuität p.a. aus dem Förderkreditvetrag
A67: Annuität 1. Kredit p.m. | B67: =B66/12 -> 4697.5531 | F67: Annuität Förderkredit p.m. | I67: =I66/12 -> 589.81827
A69: 2. Kredit | B69: für Restlaufzeit | C69: ab / im | D69: =LaufzeitKredit1+1 -> 11 | E69: . Jahr
A70: Anschlusskredit | B70: =_xlfn.XLOOKUP(BeginnFolgeKredit,'Cash & Assets'!A8:A38,'Cash & Assets'!D8:D38,0,0,1) -> 680308.7
A71: Nominalzins p.a. | B71: 0.0325 | C71: Bitte Annahme treffen!
A72: entspricht Effektivzins ca. | B72: =EFFECT(Kreditzins2,12) -> 0.032988512 | C72: bei monatl. Tilgung
A73: Restlaufzeit in Jahren | B73: =B54-B57 -> 15
A74: Ende Restlaufzeit | B74: =B58+Restlaufzeit -> 2049
A75: Annuität 2. Kredit p.a. | B75: =-PMT(Kreditzins2,Restlaufzeit,Anschlusskredit,0,0) -> 58022.563
A76: Annuität 2. Kredit p.m. | B76: =B75/12 -> 4835.2136
A78: Parameter für Rendite-Vergleiche
A79: Anlage-Rendite p.a. nominal vor Steuer | B79: 0.072 | C79: angenommene Rendite alternativer Anlagen z.B. Aktien
A80: (Grenz-)Steuersatz siehe oben | B80: =Grenzsteuersatz -> 0.42
A81: Rendite p.a. nominal nach Steuer bei o.g. (Grenz-)Steuersatz | B81: =B79*(1-B80) -> 0.04176 | C81: für Vergleich mit alternativen Kapitalanlagen
A85: Warnung
A86: Die oben angegebenen Zahlen stellen zukunftsgerichtete Planzahlen dar. Sie basieren auf:
A87: Annahmen, Schätzungen und Angeboten von Lieferanten, die nicht unter unserer Kontrolle sind.
A88: So können sich z.B. über den Betrachtungszeitraum die Steuergesetze bzw. als auch der Einkommensgrenzsteuersatz ändern.
A89: Mietausfälle bzw. Leerstandskosten ereignen sich sproadisch und nicht kontinuierlich, wie in der Modellrechnung unterstellt.
A90: Deshalb sind diese Planzahlen nur Orientierungsgrößen und müssen immer wieder überprüft und angepasst werden!
A92: Keine Gewähr für die Richtigkeit der Angaben. Dieses Tool ersetzt keine fundierte Rechts-, Steuer- oder Finanzberatung.
A95: Eine Modellrechnung liefert keine Ergebnis-Garantie!
A98: Feedback und Anregungen senden Sie bitte an:
A99: info@odenwalder-consulting.com
A102: Zellen mit "Labels"
A103: siehe Menu: FORMELN > Namensmanager

Sheet AfA
A1: AfA Varianten
I2: Wähle die Art der AfA in der Tabelle "Parameter" durch Klicken auf die Lasche aus der Dropdown-Liste aus! (siehe Abb.)
B3: AfA Varianten für Wohnimmobilen
B4: Degressiv 5% + Linear 3% | D4: 6 Jahre lang 5 %, danach 3% p,a,
B5: Degressiv 5% + Linear 2% | D5: 6 Jahre lang 5 %, danach 2% p.a.
B6: Linear 3 % p.a. | D6: 33,3 Jahre lang 3% p.a.
B7: Linear 2 % p.a. | D7: 50 Jahre lang 2 % p.a.
B8: AfA Spezial | C8: / Linear x% | D8: abhängig von der Restnutzungsdauer
B9: bei Gewerbeimmobilien bleibt es bei Linear 2 % p.a.
B12: AfA Varianten auf Gebäude über den Zeitverlauf
A15: Jahr | B15: Degressiv 5% u. Linear 3% | C15: Degressiv 5% u. Linear 2% | D15: Linear 3% | E15: Linear 2% | F15: Linear x% | J15: Siehe Information zu AfA unten im Blatt ab Zeile: 63
A16: 1 | B16: 0.05 | C16: 0.05 | D16: 0.03 | E16: 0.02 | F16: =1/Lebensdauer*(A16<=Lebensdauer) -> 0.02 | J16: Die degressive AfA (Absetzung für Abnutzung) im Überblick
A17: 2 | B17: 0.05 | C17: 0.05 | D17: 0.03 | E17: 0.02 | F17: =1/Lebensdauer*(A17<=Lebensdauer) -> 0.02
A18: 3 | B18: 0.05 | C18: 0.05 | D18: 0.03 | E18: 0.02 | F18: =1/Lebensdauer*(A18<=Lebensdauer) -> 0.02
A19: 4 | B19: 0.05 | C19: 0.05 | D19: 0.03 | E19: 0.02 | F19: =1/Lebensdauer*(A19<=Lebensdauer) -> 0.02
A20: 5 | B20: 0.05 | C20: 0.05 | D20: 0.03 | E20: 0.02 | F20: =1/Lebensdauer*(A20<=Lebensdauer) -> 0.02
A21: 6 | B21: 0.05 | C21: 0.05 | D21: 0.03 | E21: 0.02 | F21: =1/Lebensdauer*(A21<=Lebensdauer) -> 0.02
A22: 7 | B22: 0.03 | C22: 0.02 | D22: 0.03 | E22: 0.02 | F22: =1/Lebensdauer*(A22<=Lebensdauer) -> 0.02
A23: 8 | B23: 0.03 | C23: 0.02 | D23: 0.03 | E23: 0.02 | F23: =1/Lebensdauer*(A23<=Lebensdauer) -> 0.02
A24: 9 | B24: 0.03 | C24: 0.02 | D24: 0.03 | E24: 0.02 | F24: =1/Lebensdauer*(A24<=Lebensdauer) -> 0.02
A25: 10 | B25: 0.03 | C25: 0.02 | D25: 0.03 | E25: 0.02 | F25: =1/Lebensdauer*(A25<=Lebensdauer) -> 0.02
A26: 11 | B26: 0.03 | C26: 0.02 | D26: 0.03 | E26: 0.02 | F26: =1/Lebensdauer*(A26<=Lebensdauer) -> 0.02
A27: 12 | B27: 0.03 | C27: 0.02 | D27: 0.03 | E27: 0.02 | F27: =1/Lebensdauer*(A27<=Lebensdauer) -> 0.02
A28: 13 | B28: 0.03 | C28: 0.02 | D28: 0.03 | E28: 0.02 | F28: =1/Lebensdauer*(A28<=Lebensdauer) -> 0.02
... A46: 31 | B46: 0.03 | C46: 0.02 | D46: 0.03 | E46: 0.02 | F46: =1/Lebensdauer*(A46<=Lebensdauer) -> 0.02
F47: ↑
F48: Dieser
F49: Bereich kann
F50: überschrieben
F51: werden mit
F52: den relevanten
F53: AfA % Sätzen
F55: Der angezeigte
F56: %-Satz reflektiert
F57: die AfA über die
F58: Restnutzungsdauer
F59: falls diese <50 Jahre
F60: siehe Parameter B18
A63: Die degressive AfA (Absetzung für Abnutzung) im Überblick
A64: Quelle: | B64: https://www.bmwsb.bund.de/SharedDocs/kurzmeldungen/Webs/BMWSB/DE/2024/03/degressive-afa.html
A66: Die degressive Abschreibung gilt ausschließlich für neu gebaute bzw. im Jahr der Fertigstellung erworbene Wohngebäude und Wohnungen.
A67: Im ersten Jahr können fünf Prozent der Investitionskosten steuerlich geltend gemacht werden. In den folgenden Jahren können jeweils fünf Prozent des Restwertes steuerlich geltend gemacht werden.
A68: Ein Wechsel zur linearen AfA ist möglich.
A69: Der Baubeginn des Wohngebäudes muss zwischen dem 1. Oktober 2023 und dem 30. September 2029 (6-Jahres Zeitraum) liegen.
A70: Erstmals ist nicht der Bauantrag entscheidendes Kriterium für die Gewährung der degressiven AfA, sondern der angezeigte Baubeginn. So wollen wir auch die Umsetzung von Projekten anreizen, die zwar schon geplant, aber aus unterschiedlichen Gründen – z. B. Probleme bei der Finanzierung – noch nicht begonnen wurden. Damit soll auch der Bauüberhang von mehr als 800.000 genehmigten Wohnungen abgebaut werden.
A71: Beim Erwerb einer Immobilie muss der Vertrag zwischen dem 1. Oktober 2023 und dem 30. September 2029 rechtswirksam geschlossen werden. Die Immobilie muss bis zum Ende des Jahres der Fertigstellung erworben werden.
A72: Die degressive AfA kann zudem mit der Sonderabschreibung für den Mietwohnungsneubau kombiniert werden. Begünstigt werden dabei Neubauten, mit dem energetischen Gebäudestandard EH40/QNG, die eine Baukostenobergrenze von 5.200 Euro pro m² einhalten.
A73: Die Bedingungen für die genannte Sonderabschreibung für den Mietwohnungsneubau wurden mit dem Wachstumschancengesetz nochmal verbessert: Der Anwendungszeitraum für Neufälle wurde bis Ende September 2029 verlängert, die Baukostenobergrenze von 4.800 Euro pro m² auf 5.200 Euro pro m² und die begünstigten Herstellungs-/Anschaffungskosten von 2.500 Euro pro m² auf 4.000 Euro pro m² erhöht.
A76: Die degressive AfA für den Wohnungsbau beträgt 5 Prozent pro Jahr. Sie kann für Projekte mit Baubeginn zwischen dem 1. Oktober 2023 und dem 30. September 2029 in Anspruch genommen werden.
A77: Die degressive Abschreibung ist auf einen Zeitraum von sechs Jahren begrenzt. Ab dem siebten Jahr oder sobald die lineare AfA (derzeit 3 Prozent) höher ist als die degressive AfA,
A78: lohnt es sich, auf die lineare Abschreibung zu wechseln, da dann die jährliche Abschreibungsquote höher ausfällt. Also:
A79: Höhe der degressiven AfA: 5 % pro Jahr
... A162: Lineare AfA: Drei statt zwei Prozent ab dem 1.1.2023
A163: Quelle: | B163: https://www.haufe.de/immobilien/wirtschaft-politik/abschreibung-beim-mietwohnungsbau_84342_572146.html
A164: § 7 Abs. 4 Satz 1 Nr. 2 EStG: Die lineare Absetzung für Abnutzung (lineare AfA) wurde zum 1.1.2023 von zwei auf drei Prozent pro Jahr angehoben. Darauf hatten sich die Ampel-Parteien bereits im Koalitionsvertrag verständigt.
A165: Die aus dem Ansatz des höheren pauschalen AfA-Satzes resultierende kürzere Abschreibungsdauer von 33 Jahren hat aber keinen Einfluss auf die Beurteilung der tatsächlichen Nutzungsdauer von Wohngebäuden. Diese wird regelmäßig auch mehr als 50 Jahre betragen.
A166: Die Maßnahme gilt für ab dem 1.1.2023 fertiggestellte Wohngebäude (Regierungsentwurf: 30.6.2023).
A168: siehe auch: | B168: https://prozentguru.de/gebaeude-afa-3-prozent/

Sheet Cash & Assets
A1: Gewinn- und Verlust-Rechung sowie Cash-Flow-Betrachtung für eine vermietete Immobilie | J1: Asset-Werte: Immobilie, Darlehen, möglicher Überschuss aus Verkauf im Zeitverlauf | S1: Hausbank-Kredit | V1: Gewinn- u. Verlust aus Vermietung | AF1: CASH FLOW Entwicklung | AK1: Vermögenszuwachs | AO1: A S S E T Entwicklung | AU1: R E N D I T E Betrachtung
S2: plus Förderkredit | V2: Beachte: | X2: (-) = Mittelabfluß / Aufwand | AA2: (+) = Mittelzufluß / Einnahme | AG2: Mittel- | AH2: Mittel- | AI2: kumul. | AK2: kumulierter | AL2: Vermögens- | AM2: Tilgung und | AQ2: Geschätzter | AR2: Geschätzter | AS2: Überschuss | AU2: Überschuss in % | AV2: durchschn. jährliche | AW2: Überschuss in % | AX2: durchschn. jährliche
D3: Hausbank-Kredit | L3: Förderkredit | S3: Tilgung | T3: Tilgung p.a. | V3: Unterhalts- | W3: nachhaltiger | X3: =AfA_Art -> Linear 2% | Z3: Sonder-AFA | AA3: AfA p.a. | AB3: Buchwert | AC3: Zu ver- | AG3: zufluss (+) bzw. | AH3: zufluss (+) bzw. | AI3: Mittel- | AK3: Cash Flow | AL3: zuwachs aus | AM3: kumul. Cash Flow | AO3: geschätzter | AP3: geschätzter | AQ3: Verkehrswert | AR3: Verkehrswert | AS3: aus Verkauf des | AU3: bei Verkauf zu | AV3: Rendite n. Steuer | AW3: im Verhältnis | AX3: EK Rendite n. Steuer
D4: Restschuld | E4: Zins | F4: Annuität= | G4: Zinsen | H4: Sonder- | I4: Tilgung | J4: Kumul. | K4: Tilgung in % | L4: Restschuld | M4: Zins | N4: Annuität p.a. | O4: Zinsen | P4: Tilgungs- | Q4: Tilgung | R4: Kumul. | S4: p.a. | T4: in % | V4: kosten u. | W4: Ertrag aus | X4: Gebäude | Y4: AfA auf | Z4: auf | AA4: insgesamt | AB4: des Gebäudes | AC4: steuernder | AD4: (Grenz-) | AF4: Steuerzahlung | AG4: Abfluss (-) | AH4: Abfluss (-) | AI4: zu-/abfluss | AK4: angelegt u. verzinst | AL4: Tilgung und kumul. | AM4: verzinst | AO4: Marktwert | AP4: Marktwert | AQ4: (Verkaufswert) | AR4: minus | AS4: Objektes plus | AU4: Gesamtkosten von | AV4: in % aus dem | AW4: zum Eigenkapital | AX4: in % durch
C5: Eigen- | D5: Bank- | E5: in % | F5: Zins + | G5: p.a. | H5: Tilgung | I5: Hausbank- | J5: Tilgung | K5: Anfangs- | L5: Förder- | M5: Förder- | N5: Förder- | O5: Förder- | P5: zuschuss | Q5: insgesamt p.a. | R5: Tilgung | S5: insgesamt | T5: insgesamt | V5: Rücklagen u. | W5: Vermietung | X5: AFA | Y5: Gebäude | Z5: Gebäude | AA5: auf | AB5: am Ende des | AC5: Gewinn(+) | AD5: Steuer- | AF5: (+) = Ersparnis | AG5: vor Steuer | AH5: nach Steuern | AI5: nach Steuern | AK5: mit Rendite von | AL5: unverzinsten | AM5: mit Rendite von | AO5: Grundstück | AP5: Gebäude | AQ5: des Objektes | AR5: Darlehns- | AS5: kumul. Tilgung | AU5: =Investment -> 1148200 | AV5: Überschuss bei | AW5: (EK) bei einem | AX5: Überschuss bei
A6: No. | B6: Jahr | C6: kapital (EK) | D6: kredit | E6: p.a. | F6: Tilgung | G6: in € | H6: p.a. in € | I6: kredit | J6: in € | K6: kredit | L6: kredit | M6: kredit | N6: kredit | O6: kredit | P6: Förd.kredit | Q6: in € | R6: in € | S6: in € | V6: Instandhaltung | W6: in € p.a. | X6: in % | Y6: in Euro | Z6: in € | AA6: Gebäude | AB6: Jahres | AC6: Verlust(-) | AD6: satz | AF6: (-) = Zahlung | AG6: p.a. | AH6: p.a. | AI6: p.a. | AK6: =Parameter!B81 -> 0.04176 | AL6: Cash Flow | AM6: =AK6 -> 0.04176 | AO6: in € | AP6: in € | AQ6: über die Jahre | AR6: Restschuld | AS6: über die Jahre | AU6: im jeweiligen Jahr | AV6: einem Verkauf | AW6: Verkauf | AX6: einem Verkauf | AY6: Jahr
A7: =Start -> 0 | B7: Start | C7: =Eigenkapital -> 100000 | D7: =AuszahungKredit1 -> 998200 | E7: =-Kreditzins1 -> -0.0285 | F7: p.a. | H7: manuell eingeben | I7: p.a. in € | L7: =Förderkredit -> 50000 | M7: p.a. | N7: p.a. | O7: p.a. | P7: evtl. manuell eingeben | T7: =L7+D7 -> 1048200 | Z7: manuell eingeben | AB7: =AFABasis -> 924560 | AC7: aus Vermietung | AG7: =+Kreditbedarf+Förderkredit -> 1048200 | AH7: =-(Finanzbedarf+Förderkredit+Eigenkapital) -> -1198200 | AK7: nach Steuern | AM7: nach Steuern | AO7: =Grundstück -> 200000 | AP7: =Gebäude+FittingUp -> 840000 | AQ7: =AO7+AP7 -> 1040000 | AR7: =(AQ7-D7)*(D7>0) -> 41800 | AS7: =AQ7+R7+AI7-Investment -> -108200 | AU7: =AS7/$AU$5 -> -0.094234454 | AV7: =(1+AS7/$AU$5)-1 -> -0.094234454 | AW7: =IF(Eigenkapital>0,AS7/Eigenkapital,"n/a") -> -1.082 | AX7: =IF(Eigenkapital>0,(1+AW7)-1,"n/a") -> -1.082 | AY7: =B7 -> Start
A8: 1 | B8: =YEAR(Parameter!B3) -> 2026 | D8: =D7 -> 998200 | E8: =IF(A8<=LaufzeitKredit1,-Kreditzins1,IF(A8<=FinZeitraum,-Kreditzins2,0)) -> -0.0285 | F8: =IF(A8<=LaufzeitKredit1,-Annuität_Kredit_1_p.a.,IF(A8<=FinZeitraum,-Annuität_Kredit_2_p.a.,0)) -> -56370.637 | G8: =D8*E8 -> -28448.7 | H8: 0 | I8: =-F8+G8+H8 -> 27921.937 | J8: =J7+I8 -> 27921.937 | K8: =IF(D8>0,-I8/D$8,0) -> -0.027972287 | L8: =Förderkredit -> 50000 | M8: =IF(A8<=Förderzeit,-Förderzins,0) -> -0.0285 | N8: =IF(ISNUMBER(Annuität_Förderkredit),-Annuität_Förderkredit,0)*(A8<=Förderzeit) -> -7077.8193 | O8: =IF(L8>0,L8*M8,0) -> -1425 | P8: =IF(A8<=Anzahl_Tilgungszuschüsse,Tilgungszuschuss,0) -> 1500 | Q8: =-N8+O8+P8 -> 7152.8193 | R8: =Q8 -> 7152.8193 | S8: =Q8+I8 -> 35074.756 | T8: =S8/T$7 -> 0.033461893 | V8: =-Unterhaltskosten_p.a.-Instanhaltungskosten_am_Anfang -> -4564 | W8: =Parameter!B40 -> 23520 | X8: =IF(AfA_Art=AfA!B$15,VLOOKUP(A8,AfA_Tabelle,2),IF(AfA_Art=AfA!C$15,VLOOKUP(A8,AfA_Tabelle,3),IF(AfA_Art=AfA!D$15,VLOOKUP(A8,AfA_Tabelle,4),IF(AfA_Art=AfA!E$15,VLOOKUP(A8,AfA_Tabelle,5),IF(AfA_Art=AfA!F$15,VLOOKUP(A8,AfA_Tabelle,6),"tbd"))))) -> 0.02 | Y8: =IF(OR(AfA_Art=AfA!B$15,AfA_Art=AfA!C$15),-X8*AB7,IF(OR(AfA_Art=AfA!D$15,AfA_Art=AfA!E$15,AfA_Art=AfA!F$15),AFABasis*-X8,"check")) -> -18491.2 | Z8: 0 | AA8: =Y8+Z8 -> -18491.2 | AB8: =IF(AB7+AA8>=0,AB7+AA8,0) -> 906068.8 | AC8: =W8+V8+G8+AA8+O9-Disagio -> -29205.045 | AD8: =-Grenzsteuersatz -> -0.42 | AF8: =AC8*AD8 -> 12266.119 | AG8: =W8+V8+G8+Q8 -> -2339.8807 | AH8: =AG8+AF8 -> 9926.238 | AI8: =+AH8+AI7 -> 9926.238 | AK8: =AH8+(AH8/2)*AK6 -> 10133.498 | AL8: =+AI8+R8 -> 17079.057 | AM8: =+AK8+R8 -> 17286.317 | AO8: =AO7*(1+Wertzuwachst_des_Grundstücks_p.a.) -> 202000 | AP8: =AP7*(1-Wertverlust_des_Gebäudes_p.a.+Baukostensteigerung_p.a) -> 844200 | AQ8: =AP8+AO8 -> 1046200 | AR8: =(AQ8-D8) -> 48000 | AS8: =AQ8+AL8-Investment -> -84920.943 | AU8: =AS8/$AU$5 -> -0.073960062 | AV8: =(1+AU8)^(1/A8)-1 -> -0.073960062 | AW8: =IF(Eigenkapital>0,AS8/Eigenkapital,"n/a") -> -0.84920943 | AX8: =IF(Eigenkapital>0,(1+AW8)^(1/A8)-1,"n/a") -> -0.84920943 | AY8: =B8 -> 2026
A9: 2 | B9: =B8+1 -> 2027 | D9: =(A9<=FinZeitraum)*(D8-I8) -> 970278.06 | E9: =IF(A9<=LaufzeitKredit1,-Kreditzins1,IF(A9<=FinZeitraum,-Kreditzins2,0)) -> -0.0285 | F9: =IF(A9<=LaufzeitKredit1,-Annuität_Kredit_1_p.a.,IF(A9<=FinZeitraum,-Annuität_Kredit_2_p.a.,0)) -> -56370.637 | G9: =D9*E9 -> -27652.925 | H9: 0 | I9: =-F9+G9+H9 -> 28717.712 | J9: =J8+I9 -> 56639.649 | K9: =IF(D9>0,-I9/D$8,0) -> -0.028769497 | L9: =IF(L8-Q8<0,0,L8-Q8) -> 42847.181 | M9: =IF(A9<=Förderzeit,-Förderzins,0) -> -0.0285 | N9: =IF(ISNUMBER(Annuität_Förderkredit),-Annuität_Förderkredit,0)*(A9<=Förderzeit) -> -7077.8193 | O9: =IF(L9>0,L9*M9,0) -> -1221.1447 | P9: =IF(A9<=Anzahl_Tilgungszuschüsse,Tilgungszuschuss,0) -> 1500 | Q9: =-N9+O9+P9 -> 7356.6746 | R9: =R8+Q9 -> 14509.494 | S9: =Q9+I9 -> 36074.387 | T9: =S9/T$7 -> 0.034415557 | V9: =-Unterhaltskosten_p.a.*(1+Unterhaltskostensteigerung)^2 -> -2115.9225 | W9: =W8*(1+Mietpreissteigerung_p.a.) -> 23814 | X9: =IF(AfA_Art=AfA!B$15,VLOOKUP(A9,AfA_Tabelle,2),IF(AfA_Art=AfA!C$15,VLOOKUP(A9,AfA_Tabelle,3),IF(AfA_Art=AfA!D$15,VLOOKUP(A9,AfA_Tabelle,4),IF(AfA_Art=AfA!E$15,VLOOKUP(A9,AfA_Tabelle,5),IF(AfA_Art=AfA!F$15,VLOOKUP(A9,AfA_Tabelle,6),"tbd"))))) -> 0.02 | Y9: =IF(OR(AfA_Art=AfA!B$15,AfA_Art=AfA!C$15),-X9*AB8,IF(OR(AfA_Art=AfA!D$15,AfA_Art=AfA!E$15,AfA_Art=AfA!F$15),AFABasis*-X9,"check")) -> -18491.2 | Z9: 0 | AA9: =Y9+Z9 -> -18491.2 | AB9: =IF(AB8+AA9>=0,AB8+AA9,0) -> 887577.6 | AC9: =W9+V9+G9+AA9+O9 -> -25667.192 | AD9: =-Grenzsteuersatz -> -0.42 | AF9: =AC9*AD9 -> 10780.221 | AG9: =W9+V9+G9+Q9 -> 1401.8273 | AH9: =AG9+AF9 -> 12182.048 | AI9: =+AH9+AI8 -> 22108.286 | AK9: =AK8*(1+AK$6)+(AH9/2)*AK$6+AH9 -> 22993.082 | AL9: =+AI9+R9 -> 36617.78 | AM9: =+AK9+R9 -> 37502.576 | AO9: =AO8*(1+Wertzuwachst_des_Grundstücks_p.a.) -> 204020 | AP9: =AP8*(1-Wertverlust_des_Gebäudes_p.a.+Baukostensteigerung_p.a) -> 848421 | AQ9: =AP9+AO9 -> 1052441 | AR9: =(AQ9-D9) -> 82162.937 | AS9: =AQ9+AL9-Investment -> -59141.22 | AU9: =AS9/$AU$5 -> -0.051507769 | AV9: =(1+AU9)^(1/A9)-1 -> -0.026094342 | AW9: =IF(Eigenkapital>0,AS9/Eigenkapital,"n/a") -> -0.5914122 | AX9: =IF(Eigenkapital>0,(1+AW9)^(1/A9)-1,"n/a") -> -0.36079127 | AY9: =B9 -> 2027
A10: 3 | B10: =B9+1 -> 2028 | D10: =(A10<=FinZeitraum)*(D9-I9) -> 941560.35 | E10: =IF(A10<=LaufzeitKredit1,-Kreditzins1,IF(A10<=FinZeitraum,-Kreditzins2,0)) -> -0.0285 | F10: =IF(A10<=LaufzeitKredit1,-Annuität_Kredit_1_p.a.,IF(A10<=FinZeitraum,-Annuität_Kredit_2_p.a.,0)) -> -56370.637 | G10: =D10*E10 -> -26834.47 | H10: 0 | I10: =-F10+G10+H10 -> 29536.167 | J10: =J9+I10 -> 86175.816 | K10: =IF(D10>0,-I10/D$8,0) -> -0.029589428 | L10: =IF(L9-Q9<0,0,L9-Q9) -> 35490.506 | M10: =IF(A10<=Förderzeit,-Förderzins,0) -> -0.0285 | N10: =IF(ISNUMBER(Annuität_Förderkredit),-Annuität_Förderkredit,0)*(A10<=Förderzeit) -> -7077.8193 | O10: =IF(L10>0,L10*M10,0) -> -1011.4794 | P10: =IF(A10<=Anzahl_Tilgungszuschüsse,Tilgungszuschuss,0) -> 1500 | Q10: =-N10+O10+P10 -> 7566.3398 | R10: =R9+Q10 -> 22075.834 | S10: =Q10+I10 -> 37102.507 | T10: =S10/T$7 -> 0.0353964 | V10: =V9*(1+Unterhaltskostensteigerung) -> -2142.3715 | W10: =W9*(1+Mietpreissteigerung_p.a.) -> 24111.675 | X10: =IF(AfA_Art=AfA!B$15,VLOOKUP(A10,AfA_Tabelle,2),IF(AfA_Art=AfA!C$15,VLOOKUP(A10,AfA_Tabelle,3),IF(AfA_Art=AfA!D$15,VLOOKUP(A10,AfA_Tabelle,4),IF(AfA_Art=AfA!E$15,VLOOKUP(A10,AfA_Tabelle,5),IF(AfA_Art=AfA!F$15,VLOOKUP(A10,AfA_Tabelle,6),"tbd"))))) -> 0.02 | Y10: =IF(OR(AfA_Art=AfA!B$15,AfA_Art=AfA!C$15),-X10*AB9,IF(OR(AfA_Art=AfA!D$15,AfA_Art=AfA!E$15,AfA_Art=AfA!F$15),AFABasis*-X10,"check")) -> -18491.2 | Z10: 0 | AA10: =Y10+Z10 -> -18491.2 | AB10: =IF(AB9+AA10>=0,AB9+AA10,0) -> 869086.4 | AC10: =W10+V10+G10+AA10+O10 -> -24367.846 | AD10: =-Grenzsteuersatz -> -0.42 | AF10: =AC10*AD10 -> 10234.495 | AG10: =W10+V10+G10+Q10 -> 2701.1733 | AH10: =AG10+AF10 -> 12935.669 | AI10: =+AH10+AI9 -> 35043.955 | AK10: =AK9*(1+AK$6)+(AH10/2)*AK$6+AH10 -> 37159.038 | AL10: =+AI10+R10 -> 57119.788 | AM10: =+AK10+R10 -> 59234.872 | AO10: =AO9*(1+Wertzuwachst_des_Grundstücks_p.a.) -> 206060.2 | AP10: =AP9*(1-Wertverlust_des_Gebäudes_p.a.+Baukostensteigerung_p.a) -> 852663.1 | AQ10: =AP10+AO10 -> 1058723.3 | AR10: =(AQ10-D10) -> 117162.95 | AS10: =AQ10+AL10-Investment -> -32356.907 | AU10: =AS10/$AU$5 -> -0.028180549 | AV10: =(1+AU10)^(1/A10)-1 -> -0.0094831625 | AW10: =IF(Eigenkapital>0,AS10/Eigenkapital,"n/a") -> -0.32356907 | AX10: =IF(Eigenkapital>0,(1+AW10)^(1/A10)-1,"n/a") -> -0.12217525 | AY10: =B10 -> 2028
A11: 4 | B11: =B10+1 -> 2029 | D11: =(A11<=FinZeitraum)*(D10-I10) -> 912024.18 | E11: =IF(A11<=LaufzeitKredit1,-Kreditzins1,IF(A11<=FinZeitraum,-Kreditzins2,0)) -> -0.0285 | F11: =IF(A11<=LaufzeitKredit1,-Annuität_Kredit_1_p.a.,IF(A11<=FinZeitraum,-Annuität_Kredit_2_p.a.,0)) -> -56370.637 | G11: =D11*E11 -> -25992.689 | H11: 0 | I11: =-F11+G11-H11 -> 30377.948 | J11: =J10+I11 -> 116553.76 | K11: =IF(D11>0,-I11/D$8,0) -> -0.030432727 | L11: =IF(L10-Q10<0,0,L10-Q10) -> 27924.166 | M11: =IF(A11<=Förderzeit,-Förderzins,0) -> -0.0285 | N11: =IF(ISNUMBER(Annuität_Förderkredit),-Annuität_Förderkredit,0)*(A11<=Förderzeit) -> -7077.8193 | O11: =IF(L11>0,L11*M11,0) -> -795.83874 | P11: =IF(A11<=Anzahl_Tilgungszuschüsse,Tilgungszuschuss,0) -> 1500 | Q11: =-N11+O11+P11 -> 7781.9805 | R11: =R10+Q11 -> 29857.814 | S11: =Q11+I11 -> 38159.928 | T11: =S11/T$7 -> 0.036405198 | V11: =V10*(1+Unterhaltskostensteigerung) -> -2169.1512 | W11: =W10*(1+Mietpreissteigerung_p.a.) -> 24413.071 | X11: =IF(AfA_Art=AfA!B$15,VLOOKUP(A11,AfA_Tabelle,2),IF(AfA_Art=AfA!C$15,VLOOKUP(A11,AfA_Tabelle,3),IF(AfA_Art=AfA!D$15,VLOOKUP(A11,AfA_Tabelle,4),IF(AfA_Art=AfA!E$15,VLOOKUP(A11,AfA_Tabelle,5),IF(AfA_Art=AfA!F$15,VLOOKUP(A11,AfA_Tabelle,6),"tbd"))))) -> 0.02 | Y11: =IF(OR(AfA_Art=AfA!B$15,AfA_Art=AfA!C$15),-X11*AB10,IF(OR(AfA_Art=AfA!D$15,AfA_Art=AfA!E$15,AfA_Art=AfA!F$15),AFABasis*-X11,"check")) -> -18491.2 | Z11: 0 | AA11: =Y11+Z11 -> -18491.2 | AB11: =IF(AB10+AA11>=0,AB10+AA11,0) -> 850595.2 | AC11: =W11+V11+G11+AA11+O11 -> -23035.808 | AD11: =-Grenzsteuersatz -> -0.42 | AF11: =AC11*AD11 -> 9675.0395 | AG11: =W11+V11+G11+Q11 -> 4033.211 | AH11: =AG11+AF11 -> 13708.251 | AI11: =+AH11+AI10 -> 48752.205 | AK11: =AK10*(1+AK$6)+(AH11/2)*AK$6+AH11 -> 52705.279 | AL11: =+AI11+R11 -> 78610.019 | AM11: =+AK11+R11 -> 82563.093 | AO11: =AO10*(1+Wertzuwachst_des_Grundstücks_p.a.) -> 208120.8 | AP11: =AP10*(1-Wertverlust_des_Gebäudes_p.a.+Baukostensteigerung_p.a) -> 856926.42 | AQ11: =AP11+AO11 -> 1065047.2 | AR11: =(AQ11-D11) -> 153023.04 | AS11: =AQ11+AL11-Investment -> -4542.7581 | AU11: =AS11/$AU$5 -> -0.0039564171 | AV11: =(1+AU11)^(1/A11)-1 -> -0.00099057516 | AW11: =IF(Eigenkapital>0,AS11/Eigenkapital,"n/a") -> -0.045427581 | AX11: =IF(Eigenkapital>0,(1+AW11)^(1/A11)-1,"n/a") -> -0.011555656 | AY11: =B11 -> 2029
A12: 5 | B12: =B11+1 -> 2030 | D12: =(A12<=FinZeitraum)*(D11-I11) -> 881646.24 | E12: =IF(A12<=LaufzeitKredit1,-Kreditzins1,IF(A12<=FinZeitraum,-Kreditzins2,0)) -> -0.0285 | F12: =IF(A12<=LaufzeitKredit1,-Annuität_Kredit_1_p.a.,IF(A12<=FinZeitraum,-Annuität_Kredit_2_p.a.,0)) -> -56370.637 | G12: =D12*E12 -> -25126.918 | H12: 0 | I12: =-F12+G12+H12 -> 31243.719 | J12: =J11+I12 -> 147797.48 | K12: =IF(D12>0,-I12/D$8,0) -> -0.031300059 | L12: =IF(L11-Q11<0,0,L11-Q11) -> 20142.186 | M12: =IF(A12<=Förderzeit,-Förderzins,0) -> -0.0285 | N12: =IF(ISNUMBER(Annuität_Förderkredit),-Annuität_Förderkredit,0)*(A12<=Förderzeit) -> -7077.8193 | O12: =IF(L12>0,L12*M12,0) -> -574.05229 | P12: =IF(A12<=Anzahl_Tilgungszuschüsse,Tilgungszuschuss,0) -> 1500 | Q12: =-N12+O12+P12 -> 8003.767 | R12: =R11+Q12 -> 37861.581 | S12: =Q12+I12 -> 39247.486 | T12: =S12/T$7 -> 0.037442746 | V12: =V11*(1+Unterhaltskostensteigerung) -> -2196.2656 | W12: =W11*(1+Mietpreissteigerung_p.a.) -> 24718.234 | X12: =IF(AfA_Art=AfA!B$15,VLOOKUP(A12,AfA_Tabelle,2),IF(AfA_Art=AfA!C$15,VLOOKUP(A12,AfA_Tabelle,3),IF(AfA_Art=AfA!D$15,VLOOKUP(A12,AfA_Tabelle,4),IF(AfA_Art=AfA!E$15,VLOOKUP(A12,AfA_Tabelle,5),IF(AfA_Art=AfA!F$15,VLOOKUP(A12,AfA_Tabelle,6),"tbd"))))) -> 0.02 | Y12: =IF(OR(AfA_Art=AfA!B$15,AfA_Art=AfA!C$15),-X12*AB11,IF(OR(AfA_Art=AfA!D$15,AfA_Art=AfA!E$15,AfA_Art=AfA!F$15),AFABasis*-X12,"check")) -> -18491.2 | Z12: 0 | AA12: =Y12+Z12 -> -18491.2 | AB12: =IF(AB11+AA12>=0,AB11+AA12,0) -> 832104 | AC12: =W12+V12+G12+AA12+O12 -> -21670.201 | AD12: =-Grenzsteuersatz -> -0.42 | AF12: =AC12*AD12 -> 9101.4845 | AG12: =W12+V12+G12+Q12 -> 5398.818 | AH12: =AG12+AF12 -> 14500.303 | AI12: =+AH12+AI11 -> 63252.508 | AK12: =AK11*(1+AK$6)+(AH12/2)*AK$6+AH12 -> 69709.32 | AL12: =+AI12+R12 -> 101114.09 | AM12: =+AK12+R12 -> 107570.9 | AO12: =AO11*(1+Wertzuwachst_des_Grundstücks_p.a.) -> 210202.01 | AP12: =AP11*(1-Wertverlust_des_Gebäudes_p.a.+Baukostensteigerung_p.a) -> 861211.05 | AQ12: =AP12+AO12 -> 1071413.1 | AR12: =(AQ12-D12) -> 189766.83 | AS12: =AQ12+AL12-Investment -> 24327.152 | AU12: =AS12/$AU$5 -> 0.021187207 | AV12: =(1+AU12)^(1/A12)-1 -> 0.0042019795 | AW12: =IF(Eigenkapital>0,AS12/Eigenkapital,"n/a") -> 0.24327152 | AX12: =IF(Eigenkapital>0,(1+AW12)^(1/A12)-1,"n/a") -> 0.04451143 | AY12: =B12 -> 2030
A13: 6 | B13: =B12+1 -> 2031 | D13: =(A13<=FinZeitraum)*(D12-I12) -> 850402.52 | E13: =IF(A13<=LaufzeitKredit1,-Kreditzins1,IF(A13<=FinZeitraum,-Kreditzins2,0)) -> -0.0285 | F13: =IF(A13<=LaufzeitKredit1,-Annuität_Kredit_1_p.a.,IF(A13<=FinZeitraum,-Annuität_Kredit_2_p.a.,0)) -> -56370.637 | G13: =D13*E13 -> -24236.472 | H13: 0 | I13: =-F13+G13+H13 -> 32134.165 | J13: =J12+I13 -> 179931.65 | K13: =IF(D13>0,-I13/D$8,0) -> -0.032192111 | L13: =IF(L12-Q12<0,0,L12-Q12) -> 12138.419 | M13: =IF(A13<=Förderzeit,-Förderzins,0) -> -0.0285 | N13: =IF(ISNUMBER(Annuität_Förderkredit),-Annuität_Förderkredit,0)*(A13<=Förderzeit) -> -7077.8193 | O13: =IF(L13>0,L13*M13,0) -> -345.94493 | P13: =IF(A13<=Anzahl_Tilgungszuschüsse,Tilgungszuschuss,0) -> 0 | Q13: =-N13+O13+P13 -> 6731.8743 | R13: =R12+Q13 -> 44593.456 | S13: =Q13+I13 -> 38866.039 | T13: =S13/T$7 -> 0.037078839 | V13: =V12*(1+Unterhaltskostensteigerung) -> -2223.7189 | W13: =W12*(1+Mietpreissteigerung_p.a.) -> 25027.212 | X13: =IF(AfA_Art=AfA!B$15,VLOOKUP(A13,AfA_Tabelle,2),IF(AfA_Art=AfA!C$15,VLOOKUP(A13,AfA_Tabelle,3),IF(AfA_Art=AfA!D$15,VLOOKUP(A13,AfA_Tabelle,4),IF(AfA_Art=AfA!E$15,VLOOKUP(A13,AfA_Tabelle,5),IF(AfA_Art=AfA!F$15,VLOOKUP(A13,AfA_Tabelle,6),"tbd"))))) -> 0.02 | Y13: =IF(OR(AfA_Art=AfA!B$15,AfA_Art=AfA!C$15),-X13*AB12,IF(OR(AfA_Art=AfA!D$15,AfA_Art=AfA!E$15,AfA_Art=AfA!F$15),AFABasis*-X13,"check")) -> -18491.2 | Z13: 0 | AA13: =Y13+Z13 -> -18491.2 | AB13: =IF(AB12+AA13>=0,AB12+AA13,0) -> 813612.8 | AC13: =W13+V13+G13+AA13+O13 -> -20270.123 | AD13: =-Grenzsteuersatz -> -0.42 | AF13: =AC13*AD13 -> 8513.4518 | AG13: =W13+V13+G13+Q13 -> 5298.896 | AH13: =AG13+AF13 -> 13812.348 | AI13: =+AH13+AI12 -> 77064.855 | AK13: =AK12*(1+AK$6)+(AH13/2)*AK$6+AH13 -> 86721.131 | AL13: =+AI13+R13 -> 121658.31 | AM13: =+AK13+R13 -> 131314.59 | AO13: =AO12*(1+Wertzuwachst_des_Grundstücks_p.a.) -> 212304.03 | AP13: =AP12*(1-Wertverlust_des_Gebäudes_p.a.+Baukostensteigerung_p.a) -> 865517.11 | AQ13: =AP13+AO13 -> 1077821.1 | AR13: =(AQ13-D13) -> 227418.62 | AS13: =AQ13+AL13-Investment -> 51279.449 | AU13: =AS13/$AU$5 -> 0.044660729 | AV13: =(1+AU13)^(1/A13)-1 -> 0.007308607 | AW13: =IF(Eigenkapital>0,AS13/Eigenkapital,"n/a") -> 0.51279449 | AX13: =IF(Eigenkapital>0,(1+AW13)^(1/A13)-1,"n/a") -> 0.071428816 | AY13: =B13 -> 2031
A14: 7 | B14: =B13+1 -> 2032 | D14: =(A14<=FinZeitraum)*(D13-I13) -> 818268.35 | E14: =IF(A14<=LaufzeitKredit1,-Kreditzins1,IF(A14<=FinZeitraum,-Kreditzins2,0)) -> -0.0285 | F14: =IF(A14<=LaufzeitKredit1,-Annuität_Kredit_1_p.a.,IF(A14<=FinZeitraum,-Annuität_Kredit_2_p.a.,0)) -> -56370.637 | G14: =D14*E14 -> -23320.648 | H14: 0 | I14: =-F14+G14+H14 -> 33049.989 | J14: =J13+I14 -> 212981.64 | K14: =IF(D14>0,-I14/D$8,0) -> -0.033109586 | L14: =IF(L13-Q13<0,0,L13-Q13) -> 5406.5444 | M14: =IF(A14<=Förderzeit,-Förderzins,0) -> -0.0285 | N14: =IF(ISNUMBER(Annuität_Förderkredit),-Annuität_Förderkredit,0)*(A14<=Förderzeit) -> -7077.8193 | O14: =IF(L14>0,L14*M14,0) -> -154.08652 | P14: =IF(A14<=Anzahl_Tilgungszuschüsse,Tilgungszuschuss,0) -> 0 | Q14: =-N14+O14+P14 -> 6923.7328 | R14: =R13+Q14 -> 51517.188 | S14: =Q14+I14 -> 39973.722 | T14: =S14/T$7 -> 0.038135586 | V14: =V13*(1+Unterhaltskostensteigerung) -> -2251.5154 | W14: =W13*(1+Mietpreissteigerung_p.a.) -> 25340.052 | X14: =IF(AfA_Art=AfA!B$15,VLOOKUP(A14,AfA_Tabelle,2),IF(AfA_Art=AfA!C$15,VLOOKUP(A14,AfA_Tabelle,3),IF(AfA_Art=AfA!D$15,VLOOKUP(A14,AfA_Tabelle,4),IF(AfA_Art=AfA!E$15,VLOOKUP(A14,AfA_Tabelle,5),IF(AfA_Art=AfA!F$15,VLOOKUP(A14,AfA_Tabelle,6),"tbd"))))) -> 0.02 | Y14: =IF(OR(AfA_Art=AfA!B$15,AfA_Art=AfA!C$15),-X14*RBWnach6Jahren*(A14>=7),IF(OR(AfA_Art=AfA!D$15,AfA_Art=AfA!E$15,AfA_Art=AfA!F$15),AFABasis*-X14,"check")) -> -18491.2 | Z14: 0 | AA14: =Y14+Z14 -> -18491.2 | AB14: =IF(AB13+AA14>=0,AB13+AA14,0) -> 795121.6 | AC14: =W14+V14+G14+AA14+O14 -> -18877.398 | AD14: =-Grenzsteuersatz -> -0.42 | AF14: =AC14*AD14 -> 7928.507 | AG14: =W14+V14+G14+Q14 -> 6691.6217 | AH14: =AG14+AF14 -> 14620.129 | AI14: =+AH14+AI13 -> 91684.984 | AK14: =AK13*(1+AK$6)+(AH14/2)*AK$6+AH14 -> 105268 | AL14: =+AI14+R14 -> 143202.17 | AM14: =+AK14+R14 -> 156785.19 | AO14: =AO13*(1+Wertzuwachst_des_Grundstücks_p.a.) -> 214427.07 | AP14: =AP13*(1-Wertverlust_des_Gebäudes_p.a.+Baukostensteigerung_p.a) -> 869844.69 | AQ14: =AP14+AO14 -> 1084271.8 | AR14: =(AQ14-D14) -> 266003.41 | AS14: =AQ14+AL14-Investment -> 79273.936 | AU14: =AS14/$AU$5 -> 0.069041923 | AV14: =(1+AU14)^(1/A14)-1 -> 0.0095831772 | AW14: =IF(Eigenkapital>0,AS14/Eigenkapital,"n/a") -> 0.79273936 | AX14: =IF(Eigenkapital>0,(1+AW14)^(1/A14)-1,"n/a") -> 0.086967944 | AY14: =B14 -> 2032
A15: 8 | B15: =B14+1 -> 2033 | D15: =(A15<=FinZeitraum)*(D14-I14) -> 785218.36 | E15: =IF(A15<=LaufzeitKredit1,-Kreditzins1,IF(A15<=FinZeitraum,-Kreditzins2,0)) -> -0.0285 | F15: =IF(A15<=LaufzeitKredit1,-Annuität_Kredit_1_p.a.,IF(A15<=FinZeitraum,-Annuität_Kredit_2_p.a.,0)) -> -56370.637 | G15: =D15*E15 -> -22378.723 | H15: 0 | I15: =-F15+G15+H15 -> 33991.913 | J15: =J14+I15 -> 246973.55 | K15: =IF(D15>0,-I15/D$8,0) -> -0.034053209 | L15: =IF(L14-Q14<0,0,L14-Q14) -> 0 | M15: =IF(A15<=Förderzeit,-Förderzins,0) -> -0.0285 | N15: =IF(ISNUMBER(Annuität_Förderkredit),-Annuität_Förderkredit,0)*(A15<=Förderzeit) -> -7077.8193 | O15: =IF(L15>0,L15*M15,0) -> 0 | P15: =IF(A15<=Anzahl_Tilgungszuschüsse,Tilgungszuschuss,0) -> 0 | Q15: =-N15+O15+P15 -> 7077.8193 | R15: =R14+Q15 -> 58595.008 | S15: =Q15+I15 -> 41069.733 | T15: =S15/T$7 -> 0.039181199 | V15: =V14*(1+Unterhaltskostensteigerung) -> -2279.6593 | W15: =W14*(1+Mietpreissteigerung_p.a.) -> 25656.803 | X15: =IF(AfA_Art=AfA!B$15,VLOOKUP(A15,AfA_Tabelle,2),IF(AfA_Art=AfA!C$15,VLOOKUP(A15,AfA_Tabelle,3),IF(AfA_Art=AfA!D$15,VLOOKUP(A15,AfA_Tabelle,4),IF(AfA_Art=AfA!E$15,VLOOKUP(A15,AfA_Tabelle,5),IF(AfA_Art=AfA!F$15,VLOOKUP(A15,AfA_Tabelle,6),"tbd"))))) -> 0.02 | Y15: =IF(OR(AfA_Art=AfA!B$15,AfA_Art=AfA!C$15),-X15*RBWnach6Jahren*(A15>=7),IF(OR(AfA_Art=AfA!D$15,AfA_Art=AfA!E$15,AfA_Art=AfA!F$15),AFABasis*-X15,"check")) -> -18491.2 | Z15: 0 | AA15: =Y15+Z15 -> -18491.2 | AB15: =IF(AB14+AA15>=0,AB14+AA15,0) -> 776630.4 | AC15: =W15+V15+G15+AA15+O15 -> -17492.78 | AD15: =-Grenzsteuersatz -> -0.42 | AF15: =AC15*AD15 -> 7346.9674 | AG15: =W15+V15+G15+Q15 -> 8076.2397 | AH15: =AG15+AF15 -> 15423.207 | AI15: =+AH15+AI14 -> 107108.19 | AK15: =AK14*(1+AK$6)+(AH15/2)*AK$6+AH15 -> 125409.24 | AL15: =+AI15+R15 -> 165703.2 | AM15: =+AK15+R15 -> 184004.25 | AO15: =AO14*(1+Wertzuwachst_des_Grundstücks_p.a.) -> 216571.34 | AP15: =AP14*(1-Wertverlust_des_Gebäudes_p.a.+Baukostensteigerung_p.a) -> 874193.92 | AQ15: =AP15+AO15 -> 1090765.3 | AR15: =(AQ15-D15) -> 305546.89 | AS15: =AQ15+AL15-Investment -> 108268.46 | AU15: =AS15/$AU$5 -> 0.094294075 | AV15: =(1+AU15)^(1/A15)-1 -> 0.011327359 | AW15: =IF(Eigenkapital>0,AS15/Eigenkapital,"n/a") -> 1.0826846 | AX15: =IF(Eigenkapital>0,(1+AW15)^(1/A15)-1,"n/a") -> 0.09604387 | AY15: =B15 -> 2033
A16: 9 | B16: =B15+1 -> 2034 | D16: =(A16<=FinZeitraum)*(D15-I15) -> 751226.45 | E16: =IF(A16<=LaufzeitKredit1,-Kreditzins1,IF(A16<=FinZeitraum,-Kreditzins2,0)) -> -0.0285 | F16: =IF(A16<=LaufzeitKredit1,-Annuität_Kredit_1_p.a.,IF(A16<=FinZeitraum,-Annuität_Kredit_2_p.a.,0)) -> -56370.637 | G16: =D16*E16 -> -21409.954 | H16: 0 | I16: =-F16+G16+H16 -> 34960.683 | J16: =J15+I16 -> 281934.23 | K16: =IF(D16>0,-I16/D$8,0) -> -0.035023726 | L16: =IF(L15-Q15<0,0,L15-Q15) -> 0 | M16: =IF(A16<=Förderzeit,-Förderzins,0) -> 0 | N16: =IF(ISNUMBER(Annuität_Förderkredit),-Annuität_Förderkredit,0)*(A16<=Förderzeit) -> 0 | O16: =IF(L16>0,L16*M16,0) -> 0 | P16: =IF(A16<=Anzahl_Tilgungszuschüsse,Tilgungszuschuss,0) -> 0 | Q16: =-N16+O16+P16 -> 0 | R16: =R15+Q16 -> 58595.008 | S16: =Q16+I16 -> 34960.683 | T16: =S16/T$7 -> 0.033353065 | V16: =V15*(1+Unterhaltskostensteigerung) -> -2308.1551 | W16: =W15*(1+Mietpreissteigerung_p.a.) -> 25977.513 | X16: =IF(AfA_Art=AfA!B$15,VLOOKUP(A16,AfA_Tabelle,2),IF(AfA_Art=AfA!C$15,VLOOKUP(A16,AfA_Tabelle,3),IF(AfA_Art=AfA!D$15,VLOOKUP(A16,AfA_Tabelle,4),IF(AfA_Art=AfA!E$15,VLOOKUP(A16,AfA_Tabelle,5),IF(AfA_Art=AfA!F$15,VLOOKUP(A16,AfA_Tabelle,6),"tbd"))))) -> 0.02 | Y16: =IF(OR(AfA_Art=AfA!B$15,AfA_Art=AfA!C$15),-X16*RBWnach6Jahren*(A16>=7),IF(OR(AfA_Art=AfA!D$15,AfA_Art=AfA!E$15,AfA_Art=AfA!F$15),AFABasis*-X16,"check")) -> -18491.2 | Z16: 0 | AA16: =Y16+Z16 -> -18491.2 | AB16: =IF(AB15+AA16>=0,AB15+AA16,0) -> 758139.2 | AC16: =W16+V16+G16+AA16+O16 -> -16231.796 | AD16: =-Grenzsteuersatz -> -0.42 | AF16: =AC16*AD16 -> 6817.3542 | AG16: =W16+V16+G16+Q16 -> 2259.4042 | AH16: =AG16+AF16 -> 9076.7584 | AI16: =+AH16+AI15 -> 116184.95 | AK16: =AK15*(1+AK$6)+(AH16/2)*AK$6+AH16 -> 139912.61 | AL16: =+AI16+R16 -> 174779.96 | AM16: =+AK16+R16 -> 198507.62 | AO16: =AO15*(1+Wertzuwachst_des_Grundstücks_p.a.) -> 218737.05 | AP16: =AP15*(1-Wertverlust_des_Gebäudes_p.a.+Baukostensteigerung_p.a) -> 878564.89 | AQ16: =AP16+AO16 -> 1097301.9 | AR16: =(AQ16-D16) -> 346075.49 | AS16: =AQ16+AL16-Investment -> 123881.9 | AU16: =AS16/$AU$5 -> 0.10789226 | AV16: =(1+AU16)^(1/A16)-1 -> 0.011449421 | AW16: =IF(Eigenkapital>0,AS16/Eigenkapital,"n/a") -> 1.238819 | AX16: =IF(Eigenkapital>0,(1+AW16)^(1/A16)-1,"n/a") -> 0.093681832 | AY16: =B16 -> 2034
A17: 10 | B17: =B16+1 -> 2035 | D17: =(A17<=FinZeitraum)*(D16-I16) -> 716265.77 | E17: =IF(A17<=LaufzeitKredit1,-Kreditzins1,IF(A17<=FinZeitraum,-Kreditzins2,0)) -> -0.0285 | F17: =IF(A17<=LaufzeitKredit1,-Annuität_Kredit_1_p.a.,IF(A17<=FinZeitraum,-Annuität_Kredit_2_p.a.,0)) -> -56370.637 | G17: =D17*E17 -> -20413.574 | H17: 0 | I17: =-F17+G17+H17 -> 35957.062 | J17: =J16+I17 -> 317891.3 | K17: =IF(D17>0,-I17/D$8,0) -> -0.036021902 | L17: =IF(L16-Q16<0,0,L16-Q16) -> 0 | M17: =IF(A17<=Förderzeit,-Förderzins,0) -> 0 | N17: =IF(ISNUMBER(Annuität_Förderkredit),-Annuität_Förderkredit,0)*(A17<=Förderzeit) -> 0 | O17: =IF(L17>0,L17*M17,0) -> 0 | P17: =IF(A17<=Anzahl_Tilgungszuschüsse,Tilgungszuschuss,0) -> 0 | Q17: =-N17+O17+P17 -> 0 | R17: =R16+Q17 -> 58595.008 | S17: =Q17+I17 -> 35957.062 | T17: =S17/T$7 -> 0.034303628 | V17: =V16*(1+Unterhaltskostensteigerung) -> -2337.007 | W17: =W16*(1+Mietpreissteigerung_p.a.) -> 26302.232 | X17: =IF(AfA_Art=AfA!B$15,VLOOKUP(A17,AfA_Tabelle,2),IF(AfA_Art=AfA!C$15,VLOOKUP(A17,AfA_Tabelle,3),IF(AfA_Art=AfA!D$15,VLOOKUP(A17,AfA_Tabelle,4),IF(AfA_Art=AfA!E$15,VLOOKUP(A17,AfA_Tabelle,5),IF(AfA_Art=AfA!F$15,VLOOKUP(A17,AfA_Tabelle,6),"tbd"))))) -> 0.02 | Y17: =IF(OR(AfA_Art=AfA!B$15,AfA_Art=AfA!C$15),-X17*RBWnach6Jahren*(A17>=7),IF(OR(AfA_Art=AfA!D$15,AfA_Art=AfA!E$15,AfA_Art=AfA!F$15),AFABasis*-X17,"check")) -> -18491.2 | Z17: 0 | AA17: =Y17+Z17 -> -18491.2 | AB17: =IF(AB16+AA17>=0,AB16+AA17,0) -> 739648 | AC17: =W17+V17+G17+AA17+O17 -> -14939.549 | AD17: =-Grenzsteuersatz -> -0.42 | AF17: =AC17*AD17 -> 6274.6107 | AG17: =W17+V17+G17+Q17 -> 3551.6507 | AH17: =AG17+AF17 -> 9826.2614 | AI17: =+AH17+AI16 -> 126011.21 | AK17: =AK16*(1+AK$6)+(AH17/2)*AK$6+AH17 -> 155786.79 | AL17: =+AI17+R17 -> 184606.22 | AM17: =+AK17+R17 -> 214381.8 | AO17: =AO16*(1+Wertzuwachst_des_Grundstücks_p.a.) -> 220924.43 | AP17: =AP16*(1-Wertverlust_des_Gebäudes_p.a.+Baukostensteigerung_p.a) -> 882957.71 | AQ17: =AP17+AO17 -> 1103882.1 | AR17: =(AQ17-D17) -> 387616.37 | AS17: =AQ17+AL17-Investment -> 140288.35 | AU17: =AS17/$AU$5 -> 0.12218111 | AV17: =(1+AU17)^(1/A17)-1 -> 0.011594118 | AW17: =IF(Eigenkapital>0,AS17/Eigenkapital,"n/a") -> 1.4028835 | AX17: =IF(Eigenkapital>0,(1+AW17)^(1/A17)-1,"n/a") -> 0.091624495 | AY17: =B17 -> 2035
A18: 11 | B18: =B17+1 -> 2036 | D18: =(A18<=FinZeitraum)*(D17-I17) -> 680308.7 | E18: =IF(A18<=LaufzeitKredit1,-Kreditzins1,IF(A18<=FinZeitraum,-Kreditzins2,0)) -> -0.0325 | F18: =IF(A18<=LaufzeitKredit1,-Annuität_Kredit_1_p.a.,IF(A18<=FinZeitraum,-Annuität_Kredit_2_p.a.,0)) -> -58022.563 | G18: =D18*E18 -> -22110.033 | H18: 0 | I18: =-F18+G18+H18 -> 35912.53 | J18: =J17+I18 -> 353803.83 | K18: =IF(D18>0,-I18/D$8,0) -> -0.035977289 | L18: =IF(L17-Q17<0,0,L17-Q17) -> 0 | M18: =IF(A18<=Förderzeit,-Förderzins,0) -> 0 | N18: =IF(ISNUMBER(Annuität_Förderkredit),-Annuität_Förderkredit,0)*(A18<=Förderzeit) -> 0 | O18: =IF(L18>0,L18*M18,0) -> 0 | P18: =IF(A18<=Anzahl_Tilgungszuschüsse,Tilgungszuschuss,0) -> 0 | Q18: =-N18+O18+P18 -> 0 | R18: =R17+Q18 -> 58595.008 | S18: =Q18+I18 -> 35912.53 | T18: =S18/T$7 -> 0.034261143 | V18: =V17*(1+Unterhaltskostensteigerung) -> -2366.2196 | W18: =W17*(1+Mietpreissteigerung_p.a.) -> 26631.01 | X18: =IF(AfA_Art=AfA!B$15,VLOOKUP(A18,AfA_Tabelle,2),IF(AfA_Art=AfA!C$15,VLOOKUP(A18,AfA_Tabelle,3),IF(AfA_Art=AfA!D$15,VLOOKUP(A18,AfA_Tabelle,4),IF(AfA_Art=AfA!E$15,VLOOKUP(A18,AfA_Tabelle,5),IF(AfA_Art=AfA!F$15,VLOOKUP(A18,AfA_Tabelle,6),"tbd"))))) -> 0.02 | Y18: =IF(OR(AfA_Art=AfA!B$15,AfA_Art=AfA!C$15),-X18*RBWnach6Jahren*(A18>=7),IF(OR(AfA_Art=AfA!D$15,AfA_Art=AfA!E$15,AfA_Art=AfA!F$15),AFABasis*-X18,"check")) -> -18491.2 | Z18: 0 | AA18: =Y18+Z18 -> -18491.2 | AB18: =IF(AB17+AA18>=0,AB17+AA18,0) -> 721156.8 | AC18: =W18+V18+G18+AA18+O18 -> -16336.443 | AD18: =-Grenzsteuersatz -> -0.42 | AF18: =AC18*AD18 -> 6861.3059 | AG18: =W18+V18+G18+Q18 -> 2154.7574 | AH18: =AG18+AF18 -> 9016.0633 | AI18: =+AH18+AI17 -> 135027.27 | AK18: =AK17*(1+AK$6)+(AH18/2)*AK$6+AH18 -> 171496.77 | AL18: =+AI18+R18 -> 193622.28 | AM18: =+AK18+R18 -> 230091.78 | AO18: =AO17*(1+Wertzuwachst_des_Grundstücks_p.a.) -> 223133.67 | AP18: =AP17*(1-Wertverlust_des_Gebäudes_p.a.+Baukostensteigerung_p.a) -> 887372.5 | AQ18: =AP18+AO18 -> 1110506.2 | AR18: =(AQ18-D18) -> 430197.46 | AS18: =AQ18+AL18-Investment -> 155928.45 | AU18: =AS18/$AU$5 -> 0.13580252 | AV18: =(1+AU18)^(1/A18)-1 -> 0.01164358 | AW18: =IF(Eigenkapital>0,AS18/Eigenkapital,"n/a") -> 1.5592845 | AX18: =IF(Eigenkapital>0,(1+AW18)^(1/A18)-1,"n/a") -> 0.089185091 | AY18: =B18 -> 2036
A19: 12 | B19: =B18+1 -> 2037 | D19: =(A19<=FinZeitraum)*(D18-I18) -> 644396.17 | E19: =IF(A19<=LaufzeitKredit1,-Kreditzins1,IF(A19<=FinZeitraum,-Kreditzins2,0)) -> -0.0325 | F19: =IF(A19<=LaufzeitKredit1,-Annuität_Kredit_1_p.a.,IF(A19<=FinZeitraum,-Annuität_Kredit_2_p.a.,0)) -> -58022.563 | G19: =D19*E19 -> -20942.876 | H19: 0 | I19: =-F19+G19+H19 -> 37079.688 | J19: =J18+I19 -> 390883.51 | K19: =IF(D19>0,-I19/D$8,0) -> -0.037146551 | L19: =IF(L18-Q18<0,0,L18-Q18) -> 0 | M19: =IF(A19<=Förderzeit,-Förderzins,0) -> 0 | N19: =IF(ISNUMBER(Annuität_Förderkredit),-Annuität_Förderkredit,0)*(A19<=Förderzeit) -> 0 | O19: =IF(L19>0,L19*M19,0) -> 0 | P19: =IF(A19<=Anzahl_Tilgungszuschüsse,Tilgungszuschuss,0) -> 0 | Q19: =-N19+O19+P19 -> 0 | R19: =R18+Q19 -> 58595.008 | S19: =Q19+I19 -> 37079.688 | T19: =S19/T$7 -> 0.03537463 | V19: =V18*(1+Unterhaltskostensteigerung) -> -2395.7973 | W19: =W18*(1+Mietpreissteigerung_p.a.) -> 26963.898 | X19: =IF(AfA_Art=AfA!B$15,VLOOKUP(A19,AfA_Tabelle,2),IF(AfA_Art=AfA!C$15,VLOOKUP(A19,AfA_Tabelle,3),IF(AfA_Art=AfA!D$15,VLOOKUP(A19,AfA_Tabelle,4),IF(AfA_Art=AfA!E$15,VLOOKUP(A19,AfA_Tabelle,5),IF(AfA_Art=AfA!F$15,VLOOKUP(A19,AfA_Tabelle,6),"tbd"))))) -> 0.02 | Y19: =IF(OR(AfA_Art=AfA!B$15,AfA_Art=AfA!C$15),-X19*RBWnach6Jahren*(A19>=7),IF(OR(AfA_Art=AfA!D$15,AfA_Art=AfA!E$15,AfA_Art=AfA!F$15),AFABasis*-X19,"check")) -> -18491.2 | Z19: 0 | AA19: =Y19+Z19 -> -18491.2 | AB19: =IF(AB18+AA19>=0,AB18+AA19,0) -> 702665.6 | AC19: =W19+V19+G19+AA19+O19 -> -14865.975 | AD19: =-Grenzsteuersatz -> -0.42 | AF19: =AC19*AD19 -> 6243.7097 | AG19: =W19+V19+G19+Q19 -> 3625.2245 | AH19: =AG19+AF19 -> 9868.9342 | AI19: =+AH19+AI18 -> 144896.21 | AK19: =AK18*(1+AK$6)+(AH19/2)*AK$6+AH19 -> 188733.47 | AL19: =+AI19+R19 -> 203491.22 | AM19: =+AK19+R19 -> 247328.48 | AO19: =AO18*(1+Wertzuwachst_des_Grundstücks_p.a.) -> 225365.01 | AP19: =AP18*(1-Wertverlust_des_Gebäudes_p.a.+Baukostensteigerung_p.a) -> 891809.36 | AQ19: =AP19+AO19 -> 1117174.4 | AR19: =(AQ19-D19) -> 472778.19 | AS19: =AQ19+AL19-Investment -> 172465.58 | AU19: =AS19/$AU$5 -> 0.15020518 | AV19: =(1+AU19)^(1/A19)-1 -> 0.011729958 | AW19: =IF(Eigenkapital>0,AS19/Eigenkapital,"n/a") -> 1.7246558 | AX19: =IF(Eigenkapital>0,(1+AW19)^(1/A19)-1,"n/a") -> 0.087116209 | AY19: =B19 -> 2037
A20: 13 | B20: =B19+1 -> 2038 | D20: =(A20<=FinZeitraum)*(D19-I19) -> 607316.49 | E20: =IF(A20<=LaufzeitKredit1,-Kreditzins1,IF(A20<=FinZeitraum,-Kreditzins2,0)) -> -0.0325 | F20: =IF(A20<=LaufzeitKredit1,-Annuität_Kredit_1_p.a.,IF(A20<=FinZeitraum,-Annuität_Kredit_2_p.a.,0)) -> -58022.563 | G20: =D20*E20 -> -19737.786 | H20: 0 | I20: =-F20+G20+H20 -> 38284.777 | J20: =J19+I20 -> 429168.29 | K20: =IF(D20>0,-I20/D$8,0) -> -0.038353814 | L20: =IF(L19-Q19<0,0,L19-Q19) -> 0 | M20: =IF(A20<=Förderzeit,-Förderzins,0) -> 0 | N20: =IF(ISNUMBER(Annuität_Förderkredit),-Annuität_Förderkredit,0)*(A20<=Förderzeit) -> 0 | O20: =IF(L20>0,L20*M20,0) -> 0 | P20: =IF(A20<=Anzahl_Tilgungszuschüsse,Tilgungszuschuss,0) -> 0 | Q20: =-N20+O20+P20 -> 0 | R20: =R19+Q20 -> 58595.008 | S20: =Q20+I20 -> 38284.777 | T20: =S20/T$7 -> 0.036524306 | V20: =V19*(1+Unterhaltskostensteigerung) -> -2425.7448 | W20: =W19*(1+Mietpreissteigerung_p.a.) -> 27300.946 | X20: =IF(AfA_Art=AfA!B$15,VLOOKUP(A20,AfA_Tabelle,2),IF(AfA_Art=AfA!C$15,VLOOKUP(A20,AfA_Tabelle,3),IF(AfA_Art=AfA!D$15,VLOOKUP(A20,AfA_Tabelle,4),IF(AfA_Art=AfA!E$15,VLOOKUP(A20,AfA_Tabelle,5),IF(AfA_Art=AfA!F$15,VLOOKUP(A20,AfA_Tabelle,6),"tbd"))))) -> 0.02 | Y20: =IF(OR(AfA_Art=AfA!B$15,AfA_Art=AfA!C$15),-X20*RBWnach6Jahren*(A20>=7),IF(OR(AfA_Art=AfA!D$15,AfA_Art=AfA!E$15,AfA_Art=AfA!F$15),AFABasis*-X20,"check")) -> -18491.2 | Z20: 0 | AA20: =Y20+Z20 -> -18491.2 | AB20: =IF(AB19+AA20>=0,AB19+AA20,0) -> 684174.4 | AC20: =W20+V20+G20+AA20+O20 -> -13353.784 | AD20: =-Grenzsteuersatz -> -0.42 | AF20: =AC20*AD20 -> 5608.5894 | AG20: =W20+V20+G20+Q20 -> 5137.4156 | AH20: =AG20+AF20 -> 10746.005 | AI20: =+AH20+AI19 -> 155642.21 | AK20: =AK19*(1+AK$6)+(AH20/2)*AK$6+AH20 -> 207585.36 | AL20: =+AI20+R20 -> 214237.22 | AM20: =+AK20+R20 -> 266180.37 | AO20: =AO19*(1+Wertzuwachst_des_Grundstücks_p.a.) -> 227618.66 | AP20: =AP19*(1-Wertverlust_des_Gebäudes_p.a.+Baukostensteigerung_p.a) -> 896268.41 | AQ20: =AP20+AO20 -> 1123887.1 | AR20: =(AQ20-D20) -> 516570.58 | AS20: =AQ20+AL20-Investment -> 189924.29 | AU20: =AS20/$AU$5 -> 0.16541046 | AV20: =(1+AU20)^(1/A20)-1 -> 0.01184447 | AW20: =IF(Eigenkapital>0,AS20/Eigenkapital,"n/a") -> 1.8992429 | AX20: =IF(Eigenkapital>0,(1+AW20)^(1/A20)-1,"n/a") -> 0.085326366 | AY20: =B20 -> 2038
A21: 14 | B21: =B20+1 -> 2039 | D21: =(A21<=FinZeitraum)*(D20-I20) -> 569031.71 | E21: =IF(A21<=LaufzeitKredit1,-Kreditzins1,IF(A21<=FinZeitraum,-Kreditzins2,0)) -> -0.0325 | F21: =IF(A21<=LaufzeitKredit1,-Annuität_Kredit_1_p.a.,IF(A21<=FinZeitraum,-Annuität_Kredit_2_p.a.,0)) -> -58022.563 | G21: =D21*E21 -> -18493.531 | H21: 0 | I21: =-F21+G21+H21 -> 39529.033 | J21: =J20+I21 -> 468697.32 | K21: =IF(D21>0,-I21/D$8,0) -> -0.039600313 | L21: =IF(L20-Q20<0,0,L20-Q20) -> 0 | M21: =IF(A21<=Förderzeit,-Förderzins,0) -> 0 | N21: =IF(ISNUMBER(Annuität_Förderkredit),-Annuität_Förderkredit,0)*(A21<=Förderzeit) -> 0 | O21: =IF(L21>0,L21*M21,0) -> 0 | P21: =IF(A21<=Anzahl_Tilgungszuschüsse,Tilgungszuschuss,0) -> 0 | Q21: =-N21+O21+P21 -> 0 | R21: =R20+Q21 -> 58595.008 | S21: =Q21+I21 -> 39529.033 | T21: =S21/T$7 -> 0.037711346 | V21: =V20*(1+Unterhaltskostensteigerung) -> -2456.0666 | W21: =W20*(1+Mietpreissteigerung_p.a.) -> 27642.208 | X21: =IF(AfA_Art=AfA!B$15,VLOOKUP(A21,AfA_Tabelle,2),IF(AfA_Art=AfA!C$15,VLOOKUP(A21,AfA_Tabelle,3),IF(AfA_Art=AfA!D$15,VLOOKUP(A21,AfA_Tabelle,4),IF(AfA_Art=AfA!E$15,VLOOKUP(A21,AfA_Tabelle,5),IF(AfA_Art=AfA!F$15,VLOOKUP(A21,AfA_Tabelle,6),"tbd"))))) -> 0.02 | Y21: =IF(OR(AfA_Art=AfA!B$15,AfA_Art=AfA!C$15),-X21*RBWnach6Jahren*(A21>=7),IF(OR(AfA_Art=AfA!D$15,AfA_Art=AfA!E$15,AfA_Art=AfA!F$15),AFABasis*-X21,"check")) -> -18491.2 | Z21: 0 | AA21: =Y21+Z21 -> -18491.2 | AB21: =IF(AB20+AA21>=0,AB20+AA21,0) -> 665683.2 | AC21: =W21+V21+G21+AA21+O21 -> -11798.589 | AD21: =-Grenzsteuersatz -> -0.42 | AF21: =AC21*AD21 -> 4955.4074 | AG21: =W21+V21+G21+Q21 -> 6692.6109 | AH21: =AG21+AF21 -> 11648.018 | AI21: =+AH21+AI20 -> 167290.23 | AK21: =AK20*(1+AK$6)+(AH21/2)*AK$6+AH21 -> 228145.36 | AL21: =+AI21+R21 -> 225885.24 | AM21: =+AK21+R21 -> 286740.36 | AO21: =AO20*(1+Wertzuwachst_des_Grundstücks_p.a.) -> 229894.84 | AP21: =AP20*(1-Wertverlust_des_Gebäudes_p.a.+Baukostensteigerung_p.a) -> 900749.75 | AQ21: =AP21+AO21 -> 1130644.6 | AR21: =(AQ21-D21) -> 561612.88 | AS21: =AQ21+AL21-Investment -> 208329.83 | AU21: =AS21/$AU$5 -> 0.18144037 | AV21: =(1+AU21)^(1/A21)-1 -> 0.011980798 | AW21: =IF(Eigenkapital>0,AS21/Eigenkapital,"n/a") -> 2.0832983 | AX21: =IF(Eigenkapital>0,(1+AW21)^(1/A21)-1,"n/a") -> 0.083751426 | AY21: =B21 -> 2039
A22: 15 | B22: =B21+1 -> 2040 | D22: =(A22<=FinZeitraum)*(D21-I21) -> 529502.68 | E22: =IF(A22<=LaufzeitKredit1,-Kreditzins1,IF(A22<=FinZeitraum,-Kreditzins2,0)) -> -0.0325 | F22: =IF(A22<=LaufzeitKredit1,-Annuität_Kredit_1_p.a.,IF(A22<=FinZeitraum,-Annuität_Kredit_2_p.a.,0)) -> -58022.563 | G22: =D22*E22 -> -17208.837 | H22: 0 | I22: =-F22+G22+H22 -> 40813.726 | J22: =J21+I22 -> 509511.05 | K22: =IF(D22>0,-I22/D$8,0) -> -0.040887323 | L22: =IF(L21-Q21<0,0,L21-Q21) -> 0 | M22: =IF(A22<=Förderzeit,-Förderzins,0) -> 0 | N22: =IF(ISNUMBER(Annuität_Förderkredit),-Annuität_Förderkredit,0)*(A22<=Förderzeit) -> 0 | O22: =IF(L22>0,L22*M22,0) -> 0 | P22: =IF(A22<=Anzahl_Tilgungszuschüsse,Tilgungszuschuss,0) -> 0 | Q22: =-N22+O22+P22 -> 0 | R22: =R21+Q22 -> 58595.008 | S22: =Q22+I22 -> 40813.726 | T22: =S22/T$7 -> 0.038936964 | V22: =V21*(1+Unterhaltskostensteigerung) -> -2486.7674 | W22: =W21*(1+Mietpreissteigerung_p.a.) -> 27987.736 | X22: =IF(AfA_Art=AfA!B$15,VLOOKUP(A22,AfA_Tabelle,2),IF(AfA_Art=AfA!C$15,VLOOKUP(A22,AfA_Tabelle,3),IF(AfA_Art=AfA!D$15,VLOOKUP(A22,AfA_Tabelle,4),IF(AfA_Art=AfA!E$15,VLOOKUP(A22,AfA_Tabelle,5),IF(AfA_Art=AfA!F$15,VLOOKUP(A22,AfA_Tabelle,6),"tbd"))))) -> 0.02 | Y22: =IF(OR(AfA_Art=AfA!B$15,AfA_Art=AfA!C$15),-X22*RBWnach6Jahren*(A22>=7),IF(OR(AfA_Art=AfA!D$15,AfA_Art=AfA!E$15,AfA_Art=AfA!F$15),AFABasis*-X22,"check")) -> -18491.2 | Z22: 0 | AA22: =Y22+Z22 -> -18491.2 | AB22: =IF(AB21+AA22>=0,AB21+AA22,0) -> 647192 | AC22: =W22+V22+G22+AA22+O22 -> -10199.069 | AD22: =-Grenzsteuersatz -> -0.42 | AF22: =AC22*AD22 -> 4283.6089 | AG22: =W22+V22+G22+Q22 -> 8292.1313 | AH22: =AG22+AF22 -> 12575.74 | AI22: =+AH22+AI21 -> 179865.97 | AK22: =AK21*(1+AK$6)+(AH22/2)*AK$6+AH22 -> 250511.03 | AL22: =+AI22+R22 -> 238460.98 | AM22: =+AK22+R22 -> 309106.03 | AO22: =AO21*(1+Wertzuwachst_des_Grundstücks_p.a.) -> 232193.79 | AP22: =AP21*(1-Wertverlust_des_Gebäudes_p.a.+Baukostensteigerung_p.a) -> 905253.5 | AQ22: =AP22+AO22 -> 1137447.3 | AR22: =(AQ22-D22) -> 607944.61 | AS22: =AQ22+AL22-Investment -> 227708.27 | AU22: =AS22/$AU$5 -> 0.1983176 | AV22: =(1+AU22)^(1/A22)-1 -> 0.012134268 | AW22: =IF(Eigenkapital>0,AS22/Eigenkapital,"n/a") -> 2.2770827 | AX22: =IF(Eigenkapital>0,(1+AW22)^(1/A22)-1,"n/a") -> 0.082345278 | AY22: =B22 -> 2040
A23: 16 | B23: =B22+1 -> 2041 | D23: =(A23<=FinZeitraum)*(D22-I22) -> 488688.95 | E23: =IF(A23<=LaufzeitKredit1,-Kreditzins1,IF(A23<=FinZeitraum,-Kreditzins2,0)) -> -0.0325 | F23: =IF(A23<=LaufzeitKredit1,-Annuität_Kredit_1_p.a.,IF(A23<=FinZeitraum,-Annuität_Kredit_2_p.a.,0)) -> -58022.563 | G23: =D23*E23 -> -15882.391 | H23: 0 | I23: =-F23+G23+H23 -> 42140.172 | J23: =J22+I23 -> 551651.22 | K23: =IF(D23>0,-I23/D$8,0) -> -0.042216161 | L23: =IF(L22-Q22<0,0,L22-Q22) -> 0 | M23: =IF(A23<=Förderzeit,-Förderzins,0) -> 0 | N23: =IF(ISNUMBER(Annuität_Förderkredit),-Annuität_Förderkredit,0)*(A23<=Förderzeit) -> 0 | O23: =IF(L23>0,L23*M23,0) -> 0 | P23: =IF(A23<=Anzahl_Tilgungszuschüsse,Tilgungszuschuss,0) -> 0 | Q23: =-N23+O23+P23 -> 0 | R23: =R22+Q23 -> 58595.008 | S23: =Q23+I23 -> 42140.172 | T23: =S23/T$7 -> 0.040202416 | V23: =V22*(1+Unterhaltskostensteigerung) -> -2517.852 | W23: =W22*(1+Mietpreissteigerung_p.a.) -> 28337.582 | X23: =IF(AfA_Art=AfA!B$15,VLOOKUP(A23,AfA_Tabelle,2),IF(AfA_Art=AfA!C$15,VLOOKUP(A23,AfA_Tabelle,3),IF(AfA_Art=AfA!D$15,VLOOKUP(A23,AfA_Tabelle,4),IF(AfA_Art=AfA!E$15,VLOOKUP(A23,AfA_Tabelle,5),IF(AfA_Art=AfA!F$15,VLOOKUP(A23,AfA_Tabelle,6),"tbd"))))) -> 0.02 | Y23: =IF(OR(AfA_Art=AfA!B$15,AfA_Art=AfA!C$15),-X23*RBWnach6Jahren*(A23>=7),IF(OR(AfA_Art=AfA!D$15,AfA_Art=AfA!E$15,AfA_Art=AfA!F$15),AFABasis*-X23,"check")) -> -18491.2 | Z23: 0 | AA23: =Y23+Z23 -> -18491.2 | AB23: =IF(AB22+AA23>=0,AB22+AA23,0) -> 628700.8 | AC23: =W23+V23+G23+AA23+O23 -> -8553.8605 | AD23: =-Grenzsteuersatz -> -0.42 | AF23: =AC23*AD23 -> 3592.6214 | AG23: =W23+V23+G23+Q23 -> 9937.3395 | AH23: =AG23+AF23 -> 13529.961 | AI23: =+AH23+AI22 -> 193395.93 | AK23: =AK22*(1+AK$6)+(AH23/2)*AK$6+AH23 -> 274784.83 | AL23: =+AI23+R23 -> 251990.94 | AM23: =+AK23+R23 -> 333379.84 | AO23: =AO22*(1+Wertzuwachst_des_Grundstücks_p.a.) -> 234515.73 | AP23: =AP22*(1-Wertverlust_des_Gebäudes_p.a.+Baukostensteigerung_p.a) -> 909779.77 | AQ23: =AP23+AO23 -> 1144295.5 | AR23: =(AQ23-D23) -> 655606.55 | AS23: =AQ23+AL23-Investment -> 248086.44 | AU23: =AS23/$AU$5 -> 0.21606553 | AV23: =(1+AU23)^(1/A23)-1 -> 0.012301338 | AW23: =IF(Eigenkapital>0,AS23/Eigenkapital,"n/a") -> 2.4808644 | AX23: =IF(Eigenkapital>0,(1+AW23)^(1/A23)-1,"n/a") -> 0.081074053 | AY23: =B23 -> 2041
A24: 17 | B24: =B23+1 -> 2042 | D24: =(A24<=FinZeitraum)*(D23-I23) -> 446548.78 | E24: =IF(A24<=LaufzeitKredit1,-Kreditzins1,IF(A24<=FinZeitraum,-Kreditzins2,0)) -> -0.0325 | F24: =IF(A24<=LaufzeitKredit1,-Annuität_Kredit_1_p.a.,IF(A24<=FinZeitraum,-Annuität_Kredit_2_p.a.,0)) -> -58022.563 | G24: =D24*E24 -> -14512.835 | H24: 0 | I24: =-F24+G24+H24 -> 43509.728 | J24: =J23+I24 -> 595160.95 | K24: =IF(D24>0,-I24/D$8,0) -> -0.043588187 | L24: =IF(L23-Q23<0,0,L23-Q23) -> 0 | M24: =IF(A24<=Förderzeit,-Förderzins,0) -> 0 | N24: =IF(ISNUMBER(Annuität_Förderkredit),-Annuität_Förderkredit,0)*(A24<=Förderzeit) -> 0 | O24: =IF(L24>0,L24*M24,0) -> 0 | P24: =IF(A24<=Anzahl_Tilgungszuschüsse,Tilgungszuschuss,0) -> 0 | Q24: =-N24+O24+P24 -> 0 | R24: =R23+Q24 -> 58595.008 | S24: =Q24+I24 -> 43509.728 | T24: =S24/T$7 -> 0.041508994 | V24: =V23*(1+Unterhaltskostensteigerung) -> -2549.3252 | W24: =W23*(1+Mietpreissteigerung_p.a.) -> 28691.802 | X24: =IF(AfA_Art=AfA!B$15,VLOOKUP(A24,AfA_Tabelle,2),IF(AfA_Art=AfA!C$15,VLOOKUP(A24,AfA_Tabelle,3),IF(AfA_Art=AfA!D$15,VLOOKUP(A24,AfA_Tabelle,4),IF(AfA_Art=AfA!E$15,VLOOKUP(A24,AfA_Tabelle,5),IF(AfA_Art=AfA!F$15,VLOOKUP(A24,AfA_Tabelle,6),"tbd"))))) -> 0.02 | Y24: =IF(OR(AfA_Art=AfA!B$15,AfA_Art=AfA!C$15),-X24*RBWnach6Jahren*(A24>=7),IF(OR(AfA_Art=AfA!D$15,AfA_Art=AfA!E$15,AfA_Art=AfA!F$15),AFABasis*-X24,"check")) -> -18491.2 | Z24: 0 | AA24: =Y24+Z24 -> -18491.2 | AB24: =IF(AB23+AA24>=0,AB23+AA24,0) -> 610209.6 | AC24: =W24+V24+G24+AA24+O24 -> -6861.5583 | AD24: =-Grenzsteuersatz -> -0.42 | AF24: =AC24*AD24 -> 2881.8545 | AG24: =W24+V24+G24+Q24 -> 11629.642 | AH24: =AG24+AF24 -> 14511.496 | AI24: =+AH24+AI23 -> 207907.43 | AK24: =AK23*(1+AK$6)+(AH24/2)*AK$6+AH24 -> 301074.34 | AL24: =+AI24+R24 -> 266502.44 | AM24: =+AK24+R24 -> 359669.35 | AO24: =AO23*(1+Wertzuwachst_des_Grundstücks_p.a.) -> 236860.89 | AP24: =AP23*(1-Wertverlust_des_Gebäudes_p.a.+Baukostensteigerung_p.a) -> 914328.67 | AQ24: =AP24+AO24 -> 1151189.6 | AR24: =(AQ24-D24) -> 704640.77 | AS24: =AQ24+AL24-Investment -> 269491.99 | AU24: =AS24/$AU$5 -> 0.23470823 | AV24: =(1+AU24)^(1/A24)-1 -> 0.012479265 | AW24: =IF(Eigenkapital>0,AS24/Eigenkapital,"n/a") -> 2.6949199 | AX24: =IF(Eigenkapital>0,(1+AW24)^(1/A24)-1,"n/a") -> 0.079912408 | AY24: =B24 -> 2042
A25: 18 | B25: =B24+1 -> 2043 | D25: =(A25<=FinZeitraum)*(D24-I24) -> 403039.05 | E25: =IF(A25<=LaufzeitKredit1,-Kreditzins1,IF(A25<=FinZeitraum,-Kreditzins2,0)) -> -0.0325 | F25: =IF(A25<=LaufzeitKredit1,-Annuität_Kredit_1_p.a.,IF(A25<=FinZeitraum,-Annuität_Kredit_2_p.a.,0)) -> -58022.563 | G25: =D25*E25 -> -13098.769 | H25: 0 | I25: =-F25+G25+H25 -> 44923.794 | J25: =J24+I25 -> 640084.74 | K25: =IF(D25>0,-I25/D$8,0) -> -0.045004803 | L25: =IF(L24-Q24<0,0,L24-Q24) -> 0 | M25: =IF(A25<=Förderzeit,-Förderzins,0) -> 0 | N25: =IF(ISNUMBER(Annuität_Förderkredit),-Annuität_Förderkredit,0)*(A25<=Förderzeit) -> 0 | O25: =IF(L25>0,L25*M25,0) -> 0 | P25: =IF(A25<=Anzahl_Tilgungszuschüsse,Tilgungszuschuss,0) -> 0 | Q25: =-N25+O25+P25 -> 0 | R25: =R24+Q25 -> 58595.008 | S25: =Q25+I25 -> 44923.794 | T25: =S25/T$7 -> 0.042858037 | V25: =V24*(1+Unterhaltskostensteigerung) -> -2581.1917 | W25: =W24*(1+Mietpreissteigerung_p.a.) -> 29050.45 | X25: =IF(AfA_Art=AfA!B$15,VLOOKUP(A25,AfA_Tabelle,2),IF(AfA_Art=AfA!C$15,VLOOKUP(A25,AfA_Tabelle,3),IF(AfA_Art=AfA!D$15,VLOOKUP(A25,AfA_Tabelle,4),IF(AfA_Art=AfA!E$15,VLOOKUP(A25,AfA_Tabelle,5),IF(AfA_Art=AfA!F$15,VLOOKUP(A25,AfA_Tabelle,6),"tbd"))))) -> 0.02 | Y25: =IF(OR(AfA_Art=AfA!B$15,AfA_Art=AfA!C$15),-X25*RBWnach6Jahren*(A25>=7),IF(OR(AfA_Art=AfA!D$15,AfA_Art=AfA!E$15,AfA_Art=AfA!F$15),AFABasis*-X25,"check")) -> -18491.2 | Z25: 0 | AA25: =Y25+Z25 -> -18491.2 | AB25: =IF(AB24+AA25>=0,AB24+AA25,0) -> 591718.4 | AC25: =W25+V25+G25+AA25+O25 -> -5120.7112 | AD25: =-Grenzsteuersatz -> -0.42 | AF25: =AC25*AD25 -> 2150.6987 | AG25: =W25+V25+G25+Q25 -> 13370.489 | AH25: =AG25+AF25 -> 15521.188 | AI25: =+AH25+AI24 -> 223428.62 | AK25: =AK24*(1+AK$6)+(AH25/2)*AK$6+AH25 -> 329492.48 | AL25: =+AI25+R25 -> 282023.62 | AM25: =+AK25+R25 -> 388087.49 | AO25: =AO24*(1+Wertzuwachst_des_Grundstücks_p.a.) -> 239229.5 | AP25: =AP24*(1-Wertverlust_des_Gebäudes_p.a.+Baukostensteigerung_p.a) -> 918900.31 | AQ25: =AP25+AO25 -> 1158129.8 | AR25: =(AQ25-D25) -> 755090.75 | AS25: =AQ25+AL25-Investment -> 291953.43 | AU25: =AS25/$AU$5 -> 0.25427054 | AV25: =(1+AU25)^(1/A25)-1 -> 0.012665883 | AW25: =IF(Eigenkapital>0,AS25/Eigenkapital,"n/a") -> 2.9195343 | AX25: =IF(Eigenkapital>0,(1+AW25)^(1/A25)-1,"n/a") -> 0.078841068 | AY25: =B25 -> 2043
... A37: 30 | B37: =B36+1 -> 2055 | D37: =(A37<=FinZeitraum)*(D36-I36) -> 0 | E37: =IF(A37<=LaufzeitKredit1,-Kreditzins1,IF(A37<=FinZeitraum,-Kreditzins2,0)) -> 0 | F37: =IF(A37<=LaufzeitKredit1,-Annuität_Kredit_1_p.a.,IF(A37<=FinZeitraum,-Annuität_Kredit_2_p.a.,0)) -> 0 | G37: =D37*E37 -> 0 | H37: 0 | I37: =-F37+G37+H37 -> 0 | J37: =J36+I37 -> 998200 | K37: =IF(D37>0,-I37/D$8,0) -> 0 | L37: =IF(L36-Q36<0,0,L36-Q36) -> 0 | M37: =IF(A37<=Förderzeit,-Förderzins,0) -> 0 | N37: =IF(ISNUMBER(Annuität_Förderkredit),-Annuität_Förderkredit,0)*(A37<=Förderzeit) -> 0 | O37: =IF(L37>0,L37*M37,0) -> 0 | P37: =IF(A37<=Anzahl_Tilgungszuschüsse,Tilgungszuschuss,0) -> 0 | Q37: =-N37+O37+P37 -> 0 | R37: =R36+Q37 -> 58595.008 | S37: =Q37+I37 -> 0 | T37: =S37/T$7 -> 0 | V37: =V36*(1+Unterhaltskostensteigerung) -> -2996.13 | W37: =W36*(1+Mietpreissteigerung_p.a.) -> 33720.441 | X37: =IF(AfA_Art=AfA!B$15,VLOOKUP(A37,AfA_Tabelle,2),IF(AfA_Art=AfA!C$15,VLOOKUP(A37,AfA_Tabelle,3),IF(AfA_Art=AfA!D$15,VLOOKUP(A37,AfA_Tabelle,4),IF(AfA_Art=AfA!E$15,VLOOKUP(A37,AfA_Tabelle,5),IF(AfA_Art=AfA!F$15,VLOOKUP(A37,AfA_Tabelle,6),"tbd"))))) -> 0.02 | Y37: =IF(OR(AfA_Art=AfA!B$15,AfA_Art=AfA!C$15),-X37*RBWnach6Jahren*(A37>=7),IF(OR(AfA_Art=AfA!D$15,AfA_Art=AfA!E$15,AfA_Art=AfA!F$15),AFABasis*-X37,"check")) -> -18491.2 | Z37: 0 | AA37: =Y37+Z37 -> -18491.2 | AB37: =IF(AB36+AA37>=0,AB36+AA37,0) -> 369824 | AC37: =W37+V37+G37+AA37+O37 -> 12233.111 | AD37: =-Grenzsteuersatz -> -0.42 | AF37: =AC37*AD37 -> -5137.9065 | AG37: =W37+V37+G37+Q37 -> 30724.311 | AH37: =AG37+AF37 -> 25586.404 | AI37: =+AH37+AI36 -> 488661.89 | AK37: =AK36*(1+AK$6)+(AH37/2)*AK$6+AH37 -> 874124.03 | AL37: =+AI37+R37 -> 547256.89 | AM37: =+AK37+R37 -> 932719.04 | AO37: =AO36*(1+Wertzuwachst_des_Grundstücks_p.a.) -> 269569.78 | AP37: =AP36*(1-Wertverlust_des_Gebäudes_p.a.+Baukostensteigerung_p.a) -> 975576.07 | AQ37: =AP37+AO37 -> 1245145.9 | AR37: =(AQ37-D37) -> 1245145.9 | AS37: =AQ37+AL37-Investment -> 644202.75 | AU37: =AS37/$AU$5 -> 0.56105447 | AV37: =(1+AU37)^(1/A37)-1 -> 0.014956125 | AW37: =IF(Eigenkapital>0,AS37/Eigenkapital,"n/a") -> 6.4420275 | AX37: =IF(Eigenkapital>0,(1+AW37)^(1/A37)-1,"n/a") -> 0.069193662 | AY37: =B37 -> 2055
A38: 31 | B38: =B37+1 -> 2056 | D38: =(A38<=FinZeitraum)*(D37-I37) -> 0 | E38: =IF(A38<=LaufzeitKredit1,-Kreditzins1,IF(A38<=FinZeitraum,-Kreditzins2,0)) -> 0 | F38: =IF(A38<=LaufzeitKredit1,-Annuität_Kredit_1_p.a.,IF(A38<=FinZeitraum,-Annuität_Kredit_2_p.a.,0)) -> 0 | G38: =D38*E38 -> 0 | H38: 0 | I38: =-F38+G38+H38 -> 0 | J38: =J37-I38 -> 998200 | K38: =IF(D38>0,-I38/D$8,0) -> 0 | L38: =IF(L37-Q37<0,0,L37-Q37) -> 0 | M38: =IF(A38<=Förderzeit,-Förderzins,0) -> 0 | N38: =IF(ISNUMBER(Annuität_Förderkredit),-Annuität_Förderkredit,0)*(A38<=Förderzeit) -> 0 | O38: =IF(L38>0,L38*M38,0) -> 0 | P38: =IF(A38<=Anzahl_Tilgungszuschüsse,Tilgungszuschuss,0) -> 0 | Q38: =-N38+O38+P38 -> 0 | R38: =R37+Q38 -> 58595.008 | S38: =Q38+I38 -> 0 | T38: =S38/T$7 -> 0 | V38: =V37*(1+Unterhaltskostensteigerung) -> -3033.5816 | W38: =W37*(1+Mietpreissteigerung_p.a.) -> 34141.946 | X38: =IF(AfA_Art=AfA!B$15,VLOOKUP(A38,AfA_Tabelle,2),IF(AfA_Art=AfA!C$15,VLOOKUP(A38,AfA_Tabelle,3),IF(AfA_Art=AfA!D$15,VLOOKUP(A38,AfA_Tabelle,4),IF(AfA_Art=AfA!E$15,VLOOKUP(A38,AfA_Tabelle,5),IF(AfA_Art=AfA!F$15,VLOOKUP(A38,AfA_Tabelle,6),"tbd"))))) -> 0.02 | Y38: =IF(OR(AfA_Art=AfA!B$15,AfA_Art=AfA!C$15),-X38*RBWnach6Jahren*(A38>=7),IF(OR(AfA_Art=AfA!D$15,AfA_Art=AfA!E$15,AfA_Art=AfA!F$15),AFABasis*-X38,"check")) -> -18491.2 | Z38: 0 | AA38: =Y38+Z38 -> -18491.2 | AB38: =IF(AB37+AA38>=0,AB37+AA38,0) -> 351332.8 | AC38: =W38+V38+G38+AA38+O38 -> 12617.165 | AD38: =-Grenzsteuersatz -> -0.42 | AF38: =AC38*AD38 -> -5299.2091 | AG38: =W38+V38+G38+Q38 -> 31108.365 | AH38: =AG38+AF38 -> 25809.155 | AI38: =+AH38+AI37 -> 514471.04 | AK38: =AK37*(1+AK$6)+(AH38/2)*AK$6+AH38 -> 936975.5 | AL38: =+AI38+R38 -> 573066.05 | AM38: =+AK38+R38 -> 995570.51 | AO38: =AO37*(1+Wertzuwachst_des_Grundstücks_p.a.) -> 272265.48 | AP38: =AP37*(1-Wertverlust_des_Gebäudes_p.a.+Baukostensteigerung_p.a) -> 980453.95 | AQ38: =AP38+AO38 -> 1252719.4 | AR38: =(AQ38-D38) -> 1252719.4 | AS38: =AQ38+AL38-Investment -> 677585.48 | AU38: =AS38/$AU$5 -> 0.59012845 | AV38: =(1+AU38)^(1/A38)-1 -> 0.015074255 | AW38: =IF(Eigenkapital>0,AS38/Eigenkapital,"n/a") -> 6.7758548 | AX38: =IF(Eigenkapital>0,(1+AW38)^(1/A38)-1,"n/a") -> 0.068399832 | AY38: =B38 -> 2056
AK39: ↑ | AL39: ↑ | AM39: ↑ | AO39: ↑ | AP39: ↑ | AR39: ↑ | AW39: (29) / Eigenkapital
D40: (1) | E40: (2) | F40: (3) | G40: (4) | H40: (5) | I40: (6) | J40: (7) | K40: (8) | L40: (6) | M40: (7) | N40: (8) | O40: (9) | P40: (10) | Q40: (11) | R40: (12) | S40: (13) | T40: (14) | V40: (15) | W40: (16) | X40: (17) | Y40: (18) | Z40: (19) | AA40: (20) | AB40: (21) | AC40: (22) | AD40: (23) | AF40: (24) | AG40: (25) | AH40: (26) | AI40: (27) | AK40: ↑ | AL40: ↑ | AM40: ↑ | AO40: berüchsichtigt | AP40: berüchsichtigt | AQ40: (28) | AR40: ↑ | AS40: (29) | AW40: = Verkehrswert
F41: = | G41: = | H41: ↑ | I41: = | J41: ↑ | K41: = | O41: = | P41: ↑ | Q41: = | S41: = | T41: = | Y41: = -(17)* | AA41: = | AB41: =(21 aus Vor- | AC41: = | AF41: = | AG41: = | AH41: = | AK41: ↑ | AL41: kumu. Cash Flow (27) | AM41: ↑ | AO41: Inflation | AP41: Gebäudekosten- | AR41: Bonitäts- | AS41: = Verkehrs-/Verkaufswert | AW41: + kumul. Mittelzuflüsse
F42: (4)+(Tilgung) | G42: (1)*(2) | H42: Sonder- | I42: =-(3)+(4)+(5) | J42: Tilgung = | K42: (6)/Anfangs- | O42: (7)*(6) | P42: Werte | Q42: =-(8)+(9)+(10) | S42: (6)+(11) | T42: (13)/Anfangs- | Y42: (Gebäudewert aus Vorjahr) | AA42: (19)+(18) | AB42: jahr) - (20) | AC42: (16)+(4)+(8)+(15)+ | AF42: (22) * | AG42: (16)+(15)+(3)+(5)+ | AH42: (24)+(25) | AI42: ↑ | AK42: ↑ | AL42: plus | AM42: ↑ | AO42: auf Grund- | AP42: änderung | AQ42: ↑ | AR42: Status | AS42: + kumul. Mittelzuflüsse | AW42: - kumul. Mittelabfüsse
H43: tilgungen | J43: Vermögens- | K43: kredit | P43: ggf. manuell | S43: ↑ | T43: kredite | Z43: Beachte: | AC43: +(20) - Disagio | AF43: (23) | AG43: + (10) = | AH43: = | AI43: ↑ | AK43: ↑ | AL43: kumul. Tilgung (12) | AM43: ↑ | AO43: stückspreise | AP43: (Baukosten- | AQ43: ↑ | AR43: zum | AS43: - kumul. Mittelabfüsse | AW43: + kumul. Tilgungen
H44: als negative | J44: bildung bzw. | P44: eintragen! | S44: Tilgung = | Y44: [bei Degress. AfA] | Z44: AfA ist kalkulatorischer Aufwand | AG44: Mieteinkünfte | AH44: Mittelab-/zufluss | AI44: ↑ | AK44: nur sinvoll | AL44: ↑ | AM44: nur sinvoll | AP44: Inflation) | AQ44: ↑ | AR44: Jahresanfang | AS44: + kumul. Tilgungen | AW44: - Gesamtinvestition
H45: Werte | J45: Vermögens- | P45: Tilgungs- | S45: Vermögens- | Y45: bzw. | Z45: für Gewinn-/Verlustrechnung | AC45: = | AG45: - Zins und Tilgung | AH45: vor Steuern plus | AI45: ↑ | AK45: für Vergleich | AL45: ↑ | AM45: für Vergleich | AP45: und | AQ45: ↑ | AR45: ↑ | AS45: - Gesamtinvestition | AW45: dividiert durch
H46: eintragen | J46: -zuwachs | P46: zuschüsse | S46: bildung bzw. | Y46: (17)= -(16)* | Z46: aber kein Mittelabfluss | AC46: Mieteinkünfte | AF46: ↑ | AG46: incl. Sonder- | AH46: Steuerzahlung (-) | AI46: ↑ | AK46: mit alternativen | AL46: ↑ | AM46: mit alternativen | AP46: Altersabschlag | AQ46: ↑ | AR46: ↑ | AW46: Eigenkapital
A47: Warnung | P47: als positive | S47: Vermögens- | Y47: (Gebäude-Anschaffungswert) | AC47: - Betriebskosten | AF47: Achtung: | AG47: tilgungen | AH47: bzw. Steuerersparnis (+) | AK47: Kapitalanlagen | AL47: ↑ | AM47: Kapitalanlagen | AP47: für Gebäude; | AR47: ↑ | AS47: Geschätzter | AU47: Überschuss in % | AV47: Jährliche | AX47: durchschn. jährliche
A48: Die oben angegebenen Zahlen stellen zukunftsgerichtete Planzahlen dar. Sie basieren auf: | P48: Werte | S48: -zuwachs | Y48: [bei Linearer AfA] | AC48: - Instandhaltung | AF48: Mittelabfluss =(-) | AG48: - Betriebs- und | AI48: ↑ | AK48: ↑ | AL48: ↑ | AM48: ↑ | AP48: enthält keine | AQ48: Geschätzter | AR48: Geschätzter | AS48: Überschuss | AU48: bei Verkauf | AV48: Rendite p.a. in % | AX48: EK Rendite n. Steuer
A49: Annahmen, Schätzungen und Angeboten von Lieferanten, die nicht unter unserer Kontrolle sind. | P49: eintragen | AC49: - Zinsen | AF49: deshalb in | AG49: - Unterhaltskosten | AI49: ↑ | AK49: ↑ | AL49: ↑ | AM49: ↑ | AP49: anteilige | AQ49: Verkehrswert | AR49: Verkehrswert | AS49: aus Verkauf des | AU49: bezogen auf | AV49: aus dem Uberschuss | AX49: in % durch Über-
A50: So können sich z.B. über den Betrachtungszeitraum die Steuergesetze bzw. als auch der Einkommensgrenzsteuersatz ändern. | T50: KALKULATIONSLOGIK | X50: Beachte: | AC50: - AfA | AF50: Formeln mit | AI50: ↑ | AK50: kumulierter | AM50: Tilgung und | AP50: Nebenerwerbs- | AQ50: (Verkaufswert) | AR50: minus | AS50: Objektes plus | AU50: Gesamtkosten von | AV50: bei hypothetischem | AX50: schuss bei einem
A51: Mietausfälle bzw. Leerstandskosten ereignen sich sproadisch und nicht kontinuierlich, wie in der Modellrechnung unterstellt. | V51: (-) = Mittelabfluß / Aufwand | AC51: - Disagio | AF51: Pluszeichen | AH51: Cash-Aufwand | AK51: Cash Flow | AL51: Vermögens- | AM51: kumul. Cash Flow | AP51: kosten | AQ51: des Objektes | AR51: Darlehns- | AS51: kumul. Tilgung | AU51: =Investment -> 1148200 | AV51: Verkauf bezogen | AX51: Verkauf bezogen
A52: Deshalb sind diese Planzahlen nur Orientierungsgrößen und müssen immer wieder überprüft und angepasst werden! | V52: (+) = Mittelzufluß / Einnahme | AF52: da -(+) = (-) | AH52: versus | AI52: kumul. | AK52: angelegt u. verzinst | AL52: zuwachs aus | AM52: verzinst | AQ52: über die Jahre | AR52: Restschuld | AS52: über die Jahre | AU52: im jeweiligen Jahr | AV52: auf Investment | AW52: über | AX52: auf Eigenkapital
T53: Beispiel: | AC53: ↑ | AF53: und -(-) = (+) | AG53: ↑ | AH53: Vermögens- | AI53: Mittel- | AK53: mit Rendite von | AL53: Tilgung und | AM53: mit Rendite von | AP53: 5 Jahre | AQ53: =AQ12 -> 1071413.1 | AR53: =AR12 -> 189766.83 | AS53: =AS12 -> 24327.152 | AU53: =AU12 -> 0.021187207 | AV53: =AV12 -> 0.0042019795 | AW53: 5 Jahre | AX53: =AX12 -> 0.04451143
A54: Keine Gewähr für die Richtigkeit der Angaben. Dieses Tool ersetzt keine fundierte Rechts-, Steuer- oder Finanzberatung. | T54: Die Formel für den zu versteuernden Gewinn im ersten Jahr (Zelle AB8) | AC54: Achtung: | AG54: Achtung: | AH54: zuwachs | AI54: zu-/abfluss | AK54: =AK6 -> 0.04176 | AL54: kumu. Cash Flow | AM54: =AK54 -> 0.04176 | AP54: 10 Jahre | AQ54: =AQ17 -> 1103882.1 | AR54: =AR17 -> 387616.37 | AS54: =AS17 -> 140288.35 | AU54: =AU17 -> 0.12218111 | AV54: =AV17 -> 0.011594118 | AW54: 10 Jahre | AX54: =AX17 -> 0.091624495
A55: Eine Modellrechnung liefert keine Ergebnis-Garantie! | T55: lautet: AC8 = W8 + V8 +G8 + O8 + AA8 - Disagio | AC55: Mittelabfluss =(-) | AG55: Mittelabfluss =(-) | AI55: nach Steuern | AK55: nach Steuern | AL55: nach Steuern | AM55: nach Steuern | AP55: 15 Jahre | AQ55: =AQ22 -> 1137447.3 | AR55: =AR22 -> 607944.61 | AS55: =AS22 -> 227708.27 | AU55: =AU22 -> 0.1983176 | AV55: =AV22 -> 0.012134268 | AW55: 15 Jahre | AX55: =AX22 -> 0.082345278
AC56: deshalb in | AG56: deshalb in | AH56: Cash-Aufwand | AI56: =AI12 -> 63252.508 | AK56: =AK12 -> 69709.32 | AL56: =AL12 -> 101114.09 | AM56: =AM12 -> 107570.9 | AN56: über | AP56: 20 Jahre | AQ56: =AQ27 -> 1172150.3 | AR56: =AR27 -> 860418.85 | AS56: =AS27 -> 340162.36 | AU56: =AU27 -> 0.29625706 | AV56: =AV27 -> 0.013058575 | AW56: 20 Jahre | AX56: =AX27 -> 0.076913063
T57: Nur im ersten Jahr wird ein evtl. Disagio berücksichtigt. | AC57: Formeln mit | AG57: Formeln | AH57: 10 Jahre | AI57: =AI17 -> 126011.21 | AK57: =AK17 -> 155786.79 | AL57: =AL17 -> 184606.22 | AM57: =AM17 -> 214381.8 | AN57: 10 Jahre | AP57: 25 Jahre | AQ57: =AQ32 -> 1208034.7 | AR57: =AR32 -> 1151838.5 | AS57: =AS32 -> 481332.57 | AU57: =AU32 -> 0.41920621 | AV57: =AV32 -> 0.014102422 | AW57: 25 Jahre | AX57: =AX32 -> 0.072943829
A58: Feedback und Anregungen senden Sie bitte an: | T58: Deshalb findet sich in der Formel in Zelle: AC8 „-Disagio“ (im 1. Jahr) | AC58: Pluszeichen | AG58: Pluszeichen | AH58: 15 Jahre | AI58: =AI22 -> 179865.97 | AK58: =AK22 -> 250511.03 | AL58: =AL22 -> 238460.98 | AM58: =AM22 -> 309106.03 | AN58: 15 Jahre | AP58: 30 Jahre | AQ58: =AQ37 -> 1245145.9 | AR58: =AR37 -> 1245145.9 | AS58: =AS37 -> 644202.75 | AU58: =AU37 -> 0.56105447 | AV58: =AV37 -> 0.014956125 | AW58: 30 Jahre | AX58: =AX37 -> 0.069193662
A59: info@odenwalder-consulting.com | T59: im Gegensatz nur Formel in Zelle: AC9 (im 2. Jahr) | AC59: da -(+) = (-) | AG59: da -(+) = (-) | AH59: 20 Jahre | AI59: =AI27 -> 257617.06 | AK59: =AK27 -> 393194.57 | AL59: =AL27 -> 316212.07 | AM59: =AM27 -> 451789.58 | AN59: 20 Jahre | AR59: ↑ | AS59: Hypothetische
T60: Das Disagio findet sich in der "Parameter-Tabelle" in Zelle: B62 | AC60: und -(-) = (+) | AG60: und -(-) = (+) | AH60: 25 Jahre | AI60: =AI32 -> 362902.89 | AK60: =AK32 -> 598751.16 | AL60: =AL32 -> 421497.89 | AM60: =AM32 -> 657346.17 | AN60: 25 Jahre | AR60: zum Jahresanfang | AS60: Vermögens-
A61: Bevor Sie den Rechner benutzen, sollten Sie beachten: Das Programm kann Ihnen eine wichtige Orientierung über den möglichen Verlauf Ihrer Investition und die Rentabilität einer Immobilie geben – aber keine Sicherheit. In die Ergeb­nisse fließen zwangs­läufig unsichere Annahmen vor allem über die Miet­entwick­lung und den künftigen Verkaufs­erlös der Immobilie ein. Schon kleinere Änderungen bei den Prognose­annahmen können die Ergeb­nisse erheblich verändern. Rechnen Sie deshalb immer mehrere Szenarien durch und gehen Sie eher von vorsichtigen Annahmen aus. Rechnet sich die Immobilie nur bei hohen Miet­steigerungen in der Zukunft, handelt es sich letzt­lich um eine spekulative Anlage mit hohem Risiko. | T61: und wird dort als positiver Wert ausgewiesen. | AH61: 30 Jahre | AI61: =AI37 -> 488661.89 | AK61: =AK37 -> 874124.03 | AL61: =AL37 -> 547256.89 | AM61: =AM37 -> 932719.04 | AN61: 30 Jahre | AS61: änderung
T63: Ab dem zweiten Jahr lautet die Formel: AC9 = W9 + V9 +G9 + O9 + AA9
T64: bzw. (ACn) = + (-Wn) + (-Vn) + (-Gn) + (-On) + (-AAn)
T66: Der zu versteuernder Gewinn (22) | X66: errechnet sich wie folgt:
T67: =
T68: Miete (16)
T69: minus Unterhalts- und Betriebskosten (15)
T70: minus AfA insgesamt (Spalte 20)
T71: minus Schuldzinsen (4) und (7) | AC71: s
T72: minus Disagio (im 1. Jahr, falls relevant)
T74: Da in dem Spalten mit einem Mittelabfluss als auch die AfA als negative Werte (-) ausweisen werden
T75: ist die Formel (ACn) = (+Wn) + (-Vn) + (-Gn) + (-On) + (-AAn) das Äquivalent von ACn = Wn –Vn – Gn –On –AAn
T76: n steht für das n-te Jahr bzw. die Zeilen-Nummer
C77: s

Sheet Kennzahlen
B1: Jahr | C1: 1 | D1: =C1+1 -> 2 | E1: =D1+1 -> 3 | F1: =E1+1 -> 4 | G1: =F1+1 -> 5 | H1: =G1+1 -> 6 | I1: =H1+1 -> 7 | J1: =I1+1 -> 8 | K1: =J1+1 -> 9 | ... AF1: =AE1+1 -> 30
D2: (-) = Mittelabfluß / Aufwand | I2: (+) = Mittelzufluß / Einnahme
B3: Miete pro Jahr | C3: ='Cash & Assets'!B8 -> 2026 | D3: =C3+1 -> 2027 | E3: =D3+1 -> 2028 | F3: =E3+1 -> 2029 | G3: =F3+1 -> 2030 | H3: =G3+1 -> 2031 | I3: =H3+1 -> 2032 | J3: =I3+1 -> 2033 | K3: =J3+1 -> 2034 | ... AF3: =AE3+1 -> 2055
B4: Miete reduziert um Leerstandsrisko | C4: ='Cash & Assets'!$W$8 -> 23520 | D4: ='Cash & Assets'!$W$9 -> 23814 | E4: ='Cash & Assets'!W$10 -> 24111.675 | F4: ='Cash & Assets'!W$11 -> 24413.071 | G4: ='Cash & Assets'!W$12 -> 24718.234 | H4: ='Cash & Assets'!W$13 -> 25027.212 | I4: ='Cash & Assets'!W$14 -> 25340.052 | J4: ='Cash & Assets'!W$15 -> 25656.803 | K4: ='Cash & Assets'!W$16 -> 25977.513 | L4: ='Cash & Assets'!W$17 -> 26302.232 | M4: ='Cash & Assets'!W$18 -> 26631.01 | N4: ='Cash & Assets'!W$19 -> 26963.898 | O4: ='Cash & Assets'!W$20 -> 27300.946 | P4: ='Cash & Assets'!W$21 -> 27642.208 | Q4: ='Cash & Assets'!W$22 -> 27987.736 | R4: ='Cash & Assets'!W$23 -> 28337.582 | S4: ='Cash & Assets'!W$24 -> 28691.802 | T4: ='Cash & Assets'!W$25 -> 29050.45 | U4: ='Cash & Assets'!W$26 -> 29413.58 | V4: ='Cash & Assets'!W$27 -> 29781.25 | W4: ='Cash & Assets'!W$28 -> 30153.516 | X4: ='Cash & Assets'!W$29 -> 30530.435 | Y4: ='Cash & Assets'!W$30 -> 30912.065 | Z4: ='Cash & Assets'!W$31 -> 31298.466 | AA4: ='Cash & Assets'!W$32 -> 31689.697 | AB4: ='Cash & Assets'!W$33 -> 32085.818 | AC4: ='Cash & Assets'!W$34 -> 32486.891 | AD4: ='Cash & Assets'!W$35 -> 32892.977 | AE4: ='Cash & Assets'!W$36 -> 33304.139 | AF4: ='Cash & Assets'!W$37 -> 33720.441
B6: Asset-Wert-Entwicklung | C6: =C3 -> 2026 | D6: =C6+1 -> 2027 | E6: =D6+1 -> 2028 | F6: =E6+1 -> 2029 | G6: =F6+1 -> 2030 | H6: =G6+1 -> 2031 | I6: =H6+1 -> 2032 | J6: =I6+1 -> 2033 | K6: =J6+1 -> 2034 | ... AF6: =AE6+1 -> 2055
B7: Verkaufswert der Immobilie (Jahresanfang) | C7: ='Cash & Assets'!$AQ$8 -> 1046200 | D7: ='Cash & Assets'!$AQ$9 -> 1052441 | E7: ='Cash & Assets'!$AQ$10 -> 1058723.3 | F7: ='Cash & Assets'!$AQ$11 -> 1065047.2 | G7: ='Cash & Assets'!$AQ$12 -> 1071413.1 | H7: ='Cash & Assets'!$AQ$13 -> 1077821.1 | I7: ='Cash & Assets'!$AQ$14 -> 1084271.8 | J7: ='Cash & Assets'!$AQ$15 -> 1090765.3 | K7: ='Cash & Assets'!$AQ$16 -> 1097301.9 | L7: ='Cash & Assets'!$AQ$17 -> 1103882.1 | M7: ='Cash & Assets'!$AQ$18 -> 1110506.2 | N7: ='Cash & Assets'!$AQ$19 -> 1117174.4 | O7: ='Cash & Assets'!$AQ$20 -> 1123887.1 | P7: ='Cash & Assets'!$AQ$21 -> 1130644.6 | Q7: ='Cash & Assets'!$AQ$22 -> 1137447.3 | R7: ='Cash & Assets'!$AQ$23 -> 1144295.5 | S7: ='Cash & Assets'!$AQ$24 -> 1151189.6 | T7: ='Cash & Assets'!$AQ$25 -> 1158129.8 | U7: ='Cash & Assets'!$AQ$26 -> 1165116.6 | V7: ='Cash & Assets'!$AQ$27 -> 1172150.3 | W7: ='Cash & Assets'!$AQ$28 -> 1179231.2 | X7: ='Cash & Assets'!$AQ$29 -> 1186359.8 | Y7: ='Cash & Assets'!$AQ$30 -> 1193536.3 | Z7: ='Cash & Assets'!$AQ$31 -> 1200761.1 | AA7: ='Cash & Assets'!$AQ$32 -> 1208034.7 | AB7: ='Cash & Assets'!$AQ$33 -> 1215357.3 | AC7: ='Cash & Assets'!$AQ$34 -> 1222729.3 | AD7: ='Cash & Assets'!$AQ$35 -> 1230151.2 | AE7: ='Cash & Assets'!$AQ$36 -> 1237623.2 | AF7: ='Cash & Assets'!$AQ$37 -> 1245145.9
B8: Restschuld Bankkredit am Jahresanfang | C8: ='Cash & Assets'!$D8 -> 998200 | D8: ='Cash & Assets'!$D9 -> 970278.06 | E8: ='Cash & Assets'!D$10 -> 941560.35 | F8: ='Cash & Assets'!D$11 -> 912024.18 | G8: ='Cash & Assets'!D$12 -> 881646.24 | H8: ='Cash & Assets'!D$13 -> 850402.52 | I8: ='Cash & Assets'!D$14 -> 818268.35 | J8: ='Cash & Assets'!D$15 -> 785218.36 | K8: ='Cash & Assets'!D$16 -> 751226.45 | L8: ='Cash & Assets'!D$17 -> 716265.77 | M8: ='Cash & Assets'!D$18 -> 680308.7 | N8: ='Cash & Assets'!D$19 -> 644396.17 | O8: ='Cash & Assets'!D$20 -> 607316.49 | P8: ='Cash & Assets'!D$21 -> 569031.71 | Q8: ='Cash & Assets'!D$22 -> 529502.68 | R8: ='Cash & Assets'!D$23 -> 488688.95 | S8: ='Cash & Assets'!D$24 -> 446548.78 | T8: ='Cash & Assets'!D$25 -> 403039.05 | U8: ='Cash & Assets'!D$26 -> 358115.26 | V8: ='Cash & Assets'!D$27 -> 311731.44 | W8: ='Cash & Assets'!D$28 -> 263840.15 | X8: ='Cash & Assets'!D$29 -> 214392.39 | Y8: ='Cash & Assets'!D$30 -> 163337.58 | Z8: ='Cash & Assets'!D$31 -> 110623.49 | AA8: ='Cash & Assets'!D$32 -> 56196.187 | AB8: ='Cash & Assets'!D$33 -> 0 | AC8: ='Cash & Assets'!D$34 -> 0 | AD8: ='Cash & Assets'!D$35 -> 0 | AE8: ='Cash & Assets'!D$36 -> 0 | AF8: ='Cash & Assets'!D$37 -> 0
B9: Restschuld Förderkredit am Jahresanfang | C9: ='Cash & Assets'!$L8 -> 50000 | D9: ='Cash & Assets'!$L9 -> 42847.181 | E9: ='Cash & Assets'!L$10 -> 35490.506 | F9: ='Cash & Assets'!L$11 -> 27924.166 | G9: ='Cash & Assets'!L$12 -> 20142.186 | H9: ='Cash & Assets'!L$13 -> 12138.419 | I9: ='Cash & Assets'!L$14 -> 5406.5444 | J9: ='Cash & Assets'!L$15 -> 0 | K9: ='Cash & Assets'!L$16 -> 0 | L9: ='Cash & Assets'!L$17 -> 0 | M9: ='Cash & Assets'!L$18 -> 0 | N9: ='Cash & Assets'!L$19 -> 0 | O9: ='Cash & Assets'!L$20 -> 0 | P9: ='Cash & Assets'!L$21 -> 0 | Q9: ='Cash & Assets'!L$22 -> 0 | R9: ='Cash & Assets'!L$23 -> 0 | S9: ='Cash & Assets'!L$24 -> 0 | T9: ='Cash & Assets'!L$25 -> 0 | U9: ='Cash & Assets'!L$26 -> 0 | V9: ='Cash & Assets'!L$27 -> 0 | W9: ='Cash & Assets'!L$28 -> 0 | X9: ='Cash & Assets'!L$29 -> 0 | Y9: ='Cash & Assets'!L$30 -> 0 | Z9: ='Cash & Assets'!L$31 -> 0 | AA9: ='Cash & Assets'!L$32 -> 0 | AB9: ='Cash & Assets'!L$33 -> 0 | AC9: ='Cash & Assets'!L$34 -> 0 | AD9: ='Cash & Assets'!L$35 -> 0 | AE9: ='Cash & Assets'!L$36 -> 0 | AF9: ='Cash & Assets'!L$37 -> 0
B10: Restschulden insgesamt am Jahresanfang | C10: =C9+C8 -> 1048200 | D10: =D9+D8 -> 1013125.2 | E10: =E9+E8 -> 977050.86 | F10: =F9+F8 -> 939948.35 | G10: =G9+G8 -> 901788.42 | H10: =H9+H8 -> 862540.94 | I10: =I9+I8 -> 823674.9 | J10: =J9+J8 -> 785218.36 | ... AF10: =AF9+AF8 -> 0
B11: Asset-Status (Verkaufswert - Restschuld) | C11: =C7-C10 -> -2000 | D11: =D7-D10 -> 39315.756 | E11: =E7-E10 -> 81672.448 | F11: =F7-F10 -> 125098.87 | G11: =G7-G10 -> 169624.64 | H11: =H7-H10 -> 215280.2 | I11: =I7-I10 -> 260596.87 | J11: =J7-J10 -> 305546.89 | ... AF11: =AF7-AF10 -> 1245145.9
B12: Hypoth. Mittel-Überschuss bei Verkauf | C12: ='Cash & Assets'!$AS8 -> -84920.943 | D12: ='Cash & Assets'!$AS9 -> -59141.22 | E12: ='Cash & Assets'!$AS10 -> -32356.907 | F12: ='Cash & Assets'!$AS11 -> -4542.7581 | G12: ='Cash & Assets'!$AS12 -> 24327.152 | H12: ='Cash & Assets'!$AS13 -> 51279.449 | I12: ='Cash & Assets'!$AS14 -> 79273.936 | J12: ='Cash & Assets'!$AS15 -> 108268.46 | K12: ='Cash & Assets'!$AS16 -> 123881.9 | L12: ='Cash & Assets'!$AS17 -> 140288.35 | M12: ='Cash & Assets'!$AS18 -> 155928.45 | N12: ='Cash & Assets'!$AS19 -> 172465.58 | O12: ='Cash & Assets'!$AS20 -> 189924.29 | P12: ='Cash & Assets'!$AS21 -> 208329.83 | Q12: ='Cash & Assets'!$AS22 -> 227708.27 | R12: ='Cash & Assets'!$AS23 -> 248086.44 | S12: ='Cash & Assets'!$AS24 -> 269491.99 | T12: ='Cash & Assets'!$AS25 -> 291953.43 | U12: ='Cash & Assets'!$AS26 -> 315500.13 | V12: ='Cash & Assets'!$AS27 -> 340162.36 | W12: ='Cash & Assets'!$AS28 -> 365971.32 | X12: ='Cash & Assets'!$AS29 -> 392959.17 | Y12: ='Cash & Assets'!$AS30 -> 421159.04 | Z12: ='Cash & Assets'!$AS31 -> 450605.11 | AA12: ='Cash & Assets'!$AS32 -> 481332.57 | AB12: ='Cash & Assets'!$AS33 -> 513377.74 | AC12: ='Cash & Assets'!$AS34 -> 545684.3 | AD12: ='Cash & Assets'!$AS35 -> 578255.27 | AE12: ='Cash & Assets'!$AS36 -> 611093.72 | AF12: ='Cash & Assets'!$AS37 -> 644202.75
B13: Vermögen aus Tilgung + kumul. Cash Flow | C13: ='Cash & Assets'!$AL8 -> 17079.057 | D13: ='Cash & Assets'!$AL9 -> 36617.78 | E13: ='Cash & Assets'!$AL10 -> 57119.788 | F13: ='Cash & Assets'!$AL11 -> 78610.019 | G13: ='Cash & Assets'!$AL12 -> 101114.09 | H13: ='Cash & Assets'!$AL13 -> 121658.31 | I13: ='Cash & Assets'!$AL14 -> 143202.17 | J13: ='Cash & Assets'!$AL15 -> 165703.2 | K13: ='Cash & Assets'!$AL16 -> 174779.96 | L13: ='Cash & Assets'!$AL17 -> 184606.22 | M13: ='Cash & Assets'!$AL18 -> 193622.28 | N13: ='Cash & Assets'!$AL19 -> 203491.22 | O13: ='Cash & Assets'!$AL20 -> 214237.22 | P13: ='Cash & Assets'!$AL21 -> 225885.24 | Q13: ='Cash & Assets'!$AL22 -> 238460.98 | R13: ='Cash & Assets'!$AL23 -> 251990.94 | S13: ='Cash & Assets'!$AL24 -> 266502.44 | T13: ='Cash & Assets'!$AL25 -> 282023.62 | U13: ='Cash & Assets'!$AL26 -> 298583.53 | V13: ='Cash & Assets'!$AL27 -> 316212.07 | W13: ='Cash & Assets'!$AL28 -> 334940.09 | X13: ='Cash & Assets'!$AL29 -> 354799.38 | Y13: ='Cash & Assets'!$AL30 -> 375822.74 | Z13: ='Cash & Assets'!$AL31 -> 398043.97 | AA13: ='Cash & Assets'!$AL32 -> 421497.89 | AB13: ='Cash & Assets'!$AL33 -> 446220.45 | AC13: ='Cash & Assets'!$AL34 -> 471154.97 | AD13: ='Cash & Assets'!$AL35 -> 496304.09 | AE13: ='Cash & Assets'!$AL36 -> 521670.49 | AF13: ='Cash & Assets'!$AL37 -> 547256.89
B15: Mittelfuss-Entwicklung | C15: =C3 -> 2026 | D15: =C15+1 -> 2027 | E15: =D15+1 -> 2028 | F15: =E15+1 -> 2029 | G15: =F15+1 -> 2030 | H15: =G15+1 -> 2031 | I15: =H15+1 -> 2032 | J15: =I15+1 -> 2033 | K15: =J15+1 -> 2034 | ... AF15: =AE15+1 -> 2055
B16: Einnahmen - Ausgaben p.a. nach Steuer | C16: ='Cash & Assets'!AH$8 -> 9926.238 | D16: ='Cash & Assets'!$AH$9 -> 12182.048 | E16: ='Cash & Assets'!AH$10 -> 12935.669 | F16: ='Cash & Assets'!AH$11 -> 13708.251 | G16: ='Cash & Assets'!AH$12 -> 14500.303 | H16: ='Cash & Assets'!AH$13 -> 13812.348 | I16: ='Cash & Assets'!AH$14 -> 14620.129 | J16: ='Cash & Assets'!AH$15 -> 15423.207 | K16: ='Cash & Assets'!AH$16 -> 9076.7584 | L16: ='Cash & Assets'!AH$17 -> 9826.2614 | M16: ='Cash & Assets'!AH$18 -> 9016.0633 | N16: ='Cash & Assets'!AH$19 -> 9868.9342 | O16: ='Cash & Assets'!AH$20 -> 10746.005 | P16: ='Cash & Assets'!AH$21 -> 11648.018 | Q16: ='Cash & Assets'!AH$22 -> 12575.74 | R16: ='Cash & Assets'!AH$23 -> 13529.961 | S16: ='Cash & Assets'!AH$24 -> 14511.496 | T16: ='Cash & Assets'!AH$25 -> 15521.188 | U16: ='Cash & Assets'!AH$26 -> 16559.903 | V16: ='Cash & Assets'!AH$27 -> 17628.539 | W16: ='Cash & Assets'!AH$28 -> 18728.019 | X16: ='Cash & Assets'!AH$29 -> 19859.299 | Y16: ='Cash & Assets'!AH$30 -> 21023.36 | Z16: ='Cash & Assets'!AH$31 -> 22221.221 | AA16: ='Cash & Assets'!AH$32 -> 23453.927 | AB16: ='Cash & Assets'!AH$33 -> 24722.562 | AC16: ='Cash & Assets'!AH$34 -> 24934.515 | AD16: ='Cash & Assets'!AH$35 -> 25149.118 | AE16: ='Cash & Assets'!AH$36 -> 25366.403 | AF16: ='Cash & Assets'!AH$37 -> 25586.404
B17: Kumul. Einnahmen - Ausgaben nach Steuer | C17: ='Cash & Assets'!AI$8 -> 9926.238 | D17: ='Cash & Assets'!$AI$9 -> 22108.286 | E17: ='Cash & Assets'!AI$10 -> 35043.955 | F17: ='Cash & Assets'!AI$11 -> 48752.205 | G17: ='Cash & Assets'!AI$12 -> 63252.508 | H17: ='Cash & Assets'!AI$13 -> 77064.855 | I17: ='Cash & Assets'!AI$14 -> 91684.984 | J17: ='Cash & Assets'!AI$15 -> 107108.19 | K17: ='Cash & Assets'!AI$16 -> 116184.95 | L17: ='Cash & Assets'!AI$17 -> 126011.21 | M17: ='Cash & Assets'!AI$18 -> 135027.27 | N17: ='Cash & Assets'!AI$19 -> 144896.21 | O17: ='Cash & Assets'!AI$20 -> 155642.21 | P17: ='Cash & Assets'!AI$21 -> 167290.23 | Q17: ='Cash & Assets'!AI$22 -> 179865.97 | R17: ='Cash & Assets'!AI$23 -> 193395.93 | S17: ='Cash & Assets'!AI$24 -> 207907.43 | T17: ='Cash & Assets'!AI$25 -> 223428.62 | U17: ='Cash & Assets'!AI$26 -> 239988.52 | V17: ='Cash & Assets'!AI$27 -> 257617.06 | W17: ='Cash & Assets'!AI$28 -> 276345.08 | X17: ='Cash & Assets'!AI$29 -> 296204.38 | Y17: ='Cash & Assets'!AI$30 -> 317227.74 | Z17: ='Cash & Assets'!AI$31 -> 339448.96 | AA17: ='Cash & Assets'!AI$32 -> 362902.89 | AB17: ='Cash & Assets'!AI$33 -> 387625.45 | AC17: ='Cash & Assets'!AI$34 -> 412559.96 | AD17: ='Cash & Assets'!AI$35 -> 437709.08 | AE17: ='Cash & Assets'!AI$36 -> 463075.48 | AF17: ='Cash & Assets'!AI$37 -> 488661.89
B18: Mittel-Überschuss bei hypoth. Verkauf | C18: =C12 -> -84920.943 | D18: =D12 -> -59141.22 | E18: =E12 -> -32356.907 | F18: =F12 -> -4542.7581 | G18: =G12 -> 24327.152 | H18: =H12 -> 51279.449 | I18: =I12 -> 79273.936 | J18: =J12 -> 108268.46 | ... AF18: =AF12 -> 644202.75
B20: Darlehen | C20: =C$6 -> 2026 | D20: =D$6 -> 2027 | E20: =E$6 -> 2028 | F20: =F$6 -> 2029 | G20: =G$6 -> 2030 | H20: =H$6 -> 2031 | I20: =I$6 -> 2032 | J20: =J$6 -> 2033 | ... AF20: =AF$6 -> 2055
B21: Restschuld am Jahreanfang | C21: =C10 -> 1048200 | D21: =D10 -> 1013125.2 | E21: =E10 -> 977050.86 | F21: =F10 -> 939948.35 | G21: =G10 -> 901788.42 | H21: =H10 -> 862540.94 | I21: =I10 -> 823674.9 | J21: =J10 -> 785218.36 | ... AF21: =AF10 -> 0
B22: Tilgung p.a. | C22: ='Cash & Assets'!S$8 -> 35074.756 | D22: ='Cash & Assets'!$S$9 -> 36074.387 | E22: ='Cash & Assets'!S$10 -> 37102.507 | F22: ='Cash & Assets'!S$11 -> 38159.928 | G22: ='Cash & Assets'!S$12 -> 39247.486 | H22: ='Cash & Assets'!S$13 -> 38866.039 | I22: ='Cash & Assets'!S$14 -> 39973.722 | J22: ='Cash & Assets'!S$15 -> 41069.733 | K22: ='Cash & Assets'!S$16 -> 34960.683 | L22: ='Cash & Assets'!S$17 -> 35957.062 | M22: ='Cash & Assets'!Q18 -> 0 | N22: ='Cash & Assets'!S$19 -> 37079.688 | O22: ='Cash & Assets'!S$20 -> 38284.777 | P22: ='Cash & Assets'!S$21 -> 39529.033 | Q22: ='Cash & Assets'!S$22 -> 40813.726 | R22: ='Cash & Assets'!S$23 -> 42140.172 | S22: ='Cash & Assets'!S$24 -> 43509.728 | T22: ='Cash & Assets'!S$25 -> 44923.794 | U22: ='Cash & Assets'!S$26 -> 46383.817 | V22: ='Cash & Assets'!S$27 -> 47891.291 | W22: ='Cash & Assets'!S$28 -> 49447.758 | X22: ='Cash & Assets'!S$29 -> 51054.811 | Y22: ='Cash & Assets'!S$30 -> 52714.092 | Z22: ='Cash & Assets'!S$31 -> 54427.3 | AA22: ='Cash & Assets'!S$32 -> 56196.187 | AB22: ='Cash & Assets'!S$33 -> 0 | AC22: ='Cash & Assets'!S$34 -> 0 | AD22: ='Cash & Assets'!S$35 -> 0 | AE22: ='Cash & Assets'!S$36 -> 0 | AF22: ='Cash & Assets'!S$37 -> 0
B23: Kumul. Tilgung | C23: =C22 -> 35074.756 | D23: =D22+C23 -> 71149.143 | E23: =E22+D23 -> 108251.65 | F23: =F22+E23 -> 146411.58 | G23: =G22+F23 -> 185659.06 | H23: =H22+G23 -> 224525.1 | I23: =I22+H23 -> 264498.82 | J23: =J22+I23 -> 305568.56 | K23: =K22+J23 -> 340529.24 | ... AF23: =AF22+AE23 -> 1020882.5
B24: Restschuld am Jahresende | C24: =D21 -> 1013125.2 | D24: =E21 -> 977050.86 | E24: =F21 -> 939948.35 | F24: =G21 -> 901788.42 | G24: =H21 -> 862540.94 | H24: =I21 -> 823674.9 | I24: =J21 -> 785218.36 | J24: =K21 -> 751226.45 | ... AF24: =AG21 -> 0
B25: Zinsen p.a. | C25: ='Cash & Assets'!G$8+'Cash & Assets'!O$8 -> -29873.7 | D25: ='Cash & Assets'!$G$9+'Cash & Assets'!O$9 -> -28874.069 | E25: ='Cash & Assets'!G$10+'Cash & Assets'!O$10 -> -27845.949 | F25: ='Cash & Assets'!G$11+'Cash & Assets'!O$11 -> -26788.528 | G25: ='Cash & Assets'!G$12+'Cash & Assets'!O$12 -> -25700.97 | H25: ='Cash & Assets'!G$13+'Cash & Assets'!O$13 -> -24582.417 | I25: ='Cash & Assets'!G$14+'Cash & Assets'!O$14 -> -23474.735 | J25: ='Cash & Assets'!G$15+'Cash & Assets'!O$15 -> -22378.723 | K25: ='Cash & Assets'!G$16+'Cash & Assets'!O$16 -> -21409.954 | L25: ='Cash & Assets'!G$17+'Cash & Assets'!O$17 -> -20413.574 | M25: ='Cash & Assets'!G$18+'Cash & Assets'!O$18 -> -22110.033 | N25: ='Cash & Assets'!G$19+'Cash & Assets'!O$19 -> -20942.876 | O25: ='Cash & Assets'!G$20+'Cash & Assets'!O$20 -> -19737.786 | P25: ='Cash & Assets'!G$21+'Cash & Assets'!O$21 -> -18493.531 | Q25: ='Cash & Assets'!G$22+'Cash & Assets'!O$22 -> -17208.837 | R25: ='Cash & Assets'!G$23+'Cash & Assets'!O$23 -> -15882.391 | S25: ='Cash & Assets'!G$24+'Cash & Assets'!O$24 -> -14512.835 | T25: ='Cash & Assets'!G$25+'Cash & Assets'!O$25 -> -13098.769 | U25: ='Cash & Assets'!G$26+'Cash & Assets'!O$26 -> -11638.746 | V25: ='Cash & Assets'!G$27+'Cash & Assets'!O$27 -> -10131.272 | W25: ='Cash & Assets'!G$28+'Cash & Assets'!O$28 -> -8574.8048 | X25: ='Cash & Assets'!G$29+'Cash & Assets'!O$29 -> -6967.7527 | Y25: ='Cash & Assets'!G$30+'Cash & Assets'!O$30 -> -5308.4713 | Z25: ='Cash & Assets'!G$31+'Cash & Assets'!O$31 -> -3595.2633 | AA25: ='Cash & Assets'!G$32+'Cash & Assets'!O$32 -> -1826.3761 | AB25: ='Cash & Assets'!G$33+'Cash & Assets'!O$33 -> 0 | AC25: ='Cash & Assets'!G$34+'Cash & Assets'!O$34 -> 0 | AD25: ='Cash & Assets'!G$35+'Cash & Assets'!O$35 -> 0 | AE25: ='Cash & Assets'!G$36+'Cash & Assets'!O$36 -> 0 | AF25: ='Cash & Assets'!G$37+'Cash & Assets'!O$37 -> 0
B26: Annuität / Kapitaldienst p.a. | C26: ='Cash & Assets'!F$8+'Cash & Assets'!N$8 -> -63448.456 | D26: ='Cash & Assets'!$F$9+'Cash & Assets'!N$9 -> -63448.456 | E26: ='Cash & Assets'!F$10+'Cash & Assets'!N$10 -> -63448.456 | F26: ='Cash & Assets'!F$11+'Cash & Assets'!N$11 -> -63448.456 | G26: ='Cash & Assets'!F$12+'Cash & Assets'!N$12 -> -63448.456 | H26: ='Cash & Assets'!F$13+'Cash & Assets'!N$13 -> -63448.456 | I26: ='Cash & Assets'!F$14+'Cash & Assets'!N$14 -> -63448.456 | J26: ='Cash & Assets'!F$15+'Cash & Assets'!N$15 -> -63448.456 | K26: ='Cash & Assets'!F$16+'Cash & Assets'!N$16 -> -56370.637 | L26: ='Cash & Assets'!F$17+'Cash & Assets'!N$17 -> -56370.637 | M26: ='Cash & Assets'!F$18+'Cash & Assets'!N$18 -> -58022.563 | N26: ='Cash & Assets'!F$19+'Cash & Assets'!N$19 -> -58022.563 | O26: ='Cash & Assets'!F$20+'Cash & Assets'!N$20 -> -58022.563 | P26: ='Cash & Assets'!F$21+'Cash & Assets'!N$21 -> -58022.563 | Q26: ='Cash & Assets'!F$22+'Cash & Assets'!N$22 -> -58022.563 | R26: ='Cash & Assets'!F$23+'Cash & Assets'!N$23 -> -58022.563 | S26: ='Cash & Assets'!F$24+'Cash & Assets'!N$24 -> -58022.563 | T26: ='Cash & Assets'!F$25+'Cash & Assets'!N$25 -> -58022.563 | U26: ='Cash & Assets'!F$26+'Cash & Assets'!N$26 -> -58022.563 | V26: ='Cash & Assets'!F$27+'Cash & Assets'!N$27 -> -58022.563 | W26: ='Cash & Assets'!F$28+'Cash & Assets'!N$28 -> -58022.563 | X26: ='Cash & Assets'!F$29+'Cash & Assets'!N$29 -> -58022.563 | Y26: ='Cash & Assets'!F$30+'Cash & Assets'!N$30 -> -58022.563 | Z26: ='Cash & Assets'!F$31+'Cash & Assets'!N$31 -> -58022.563 | AA26: ='Cash & Assets'!F$32+'Cash & Assets'!N$32 -> -58022.563 | AB26: ='Cash & Assets'!F$33+'Cash & Assets'!N$33 -> 0 | AC26: ='Cash & Assets'!F$34+'Cash & Assets'!N$34 -> 0 | AD26: ='Cash & Assets'!F$35+'Cash & Assets'!N$35 -> 0 | AE26: ='Cash & Assets'!F$36+'Cash & Assets'!N$36 -> 0 | AF26: ='Cash & Assets'!F$37+'Cash & Assets'!N$37 -> 0
B29: Keine Gewähr für die Richtigkeit der Angaben. Dieses Tool ersetzt keine fundierte Rechts-, Steuer- oder Finanzberatung. | L29: Objekt und Größe
B30: Eine Modellrechnung liefert keine Ergebnis-Garantie! | L30: Adresse | M30: =Parameter!G2 -> Musterstraße 123, 45678 Irgendwo
L31: Nutz- u. | N31: Gesamtinvestition | O31: =Parameter!B16 -> 1148200
B32: Warnung | L32: Wohnfläche | M32: =Parameter!B7 -> 144 | N32: Grundstück | O32: =Parameter!I3 -> 500
B33: Die oben angegebenen Zahlen stellen zukunftsgerichtete Planzahlen dar. Sie basieren auf:
B34: Annahmen, Schätzungen und Angeboten von Lieferanten, die nicht unter unserer Kontrolle sind.
B35: So können sich z.B. über den Betrachtungszeitraum die Steuergesetze bzw. als auch der Einkommensgrenzsteuersatz ändern.
B36: Mietausfälle bzw. Leerstandskosten ereignen sich sproadisch und nicht kontinuierlich, wie in der Modellrechnung unterstellt.
B37: Deshalb sind diese Planzahlen nur Orientierungsgrößen und müssen immer wieder überprüft und angepasst werden!
B41: Feedback und Anregungen senden Sie bitte an:
B42: info@odenwalder-consulting.com

Sheet Graphiken
B1: Objekt
B2: Adresse | C2: =Parameter!G2 -> Musterstraße 123, 45678 Irgendwo
B3: Nutz- u. | D3: Gesamtinvestition | E3: =Parameter!B16 -> 1148200
B4: Wohnfläche | C4: =Parameter!G3 -> 144 | D4: Grundstück | E4: =Parameter!I3 -> 500
C36: Hypothetischer Vermögenszuwachs errechnet sich aus: | L36: Die "Vermögensänderung" errechnet sich aus dem Mittelzu- und
C37: + geschätzter Verkaufspreis zum jeweiligen Zeitpunkt | L37: Mittelabfluss (Cash Flow), der die Annunität (=Zins + Tilgung) enthält, reduziert um die Tilgung,
C38: - eingebrachtes Eigenkapital | L38: wie folgt: | S38: Geschätzter
C39: - Restschuld aus Darlehn zum jeweiligen Zeitpunkt | L39: + Miete | R39: Vermögens- | S39: Überschuss
C40: - kumul. Tilgung bis zum jeweiligen Zeitpunkt | L40: - laufende Kosten (Instandh. & Rücklagen) | R40: zuwachs aus | S40: aus Verkauf des
L41: - Erwerbsnebenkosten (am Anfang) | R41: Tilgung und | S41: Objektes plus | T41: Verkaufspreis
C42: Warum ist der Vermögenszuwachs am Anfang oft negativ? | L42: - Zinsen (oder Annuität - Tilgung) | R42: kumu. Cash Flow | S42: kumul. Tilgung | T42: minus
C43: Die Nebenserwerbskosten, wie Makler, Grundsteuer, etc, die am Anfang anfallen, | L43: - Steuerzahlung bzw. | Q43: nach | R43: nach Steuern | S43: über die Jahre | T43: Restschuld
C44: erhöhen das Kreditvolumen. Bei einem Verkauf einer Immobilie in den Anfangsjahren | L44: + Steuerersparnis (wenn relevant) | Q44: 5 Jahre | R44: ='Cash & Assets'!AL56 -> 101114.09 | S44: ='Cash & Assets'!AS53 -> 24327.152 | T44: ='Cash & Assets'!AR53 -> 189766.83
C45: ist die Summe aus kumulierter Tilgung und der Differenz aus (Verkaufserlös - Restschuld) | L45: Hier wird kein Überschuss oder Verlust aus einem | Q45: 10 Jahre | R45: ='Cash & Assets'!AL57 -> 184606.22 | S45: ='Cash & Assets'!AS54 -> 140288.35 | T45: ='Cash & Assets'!AR54 -> 387616.37
C46: meist kleiner als die Summe der Erwerbsnebenkosten. | L46: hypothetischen Verkauf der Immobilie berücksichtigt! | Q46: 15 Jahre | R46: ='Cash & Assets'!AL58 -> 238460.98 | S46: ='Cash & Assets'!AS55 -> 227708.27 | T46: ='Cash & Assets'!AR55 -> 607944.61
Q47: 20 Jahre | R47: ='Cash & Assets'!AL59 -> 316212.07 | S47: ='Cash & Assets'!AS56 -> 340162.36 | T47: ='Cash & Assets'!AR56 -> 860418.85
Q48: 25 Jahre | R48: ='Cash & Assets'!AL60 -> 421497.89 | S48: ='Cash & Assets'!AS57 -> 481332.57 | T48: ='Cash & Assets'!AR57 -> 1151838.5
Q49: 30 Jahre | R49: ='Cash & Assets'!AL61 -> 547256.89 | S49: ='Cash & Assets'!AS58 -> 644202.75 | T49: ='Cash & Assets'!AR58 -> 1245145.9
R50: Vermögens- | S50: Vermögens- | T50: Bonitäts-Status
R51: änderung | S51: änderung
P114: Cash-Aufwand | R114: Vermögens- | S114: Geschätzter | T114: Geschätzter
P115: versus | Q115: kumul. | R115: zuwachs aus | S115: Überschuss | T115: Verkehrswert
P116: Vermögens- | Q116: Mittel- | R116: Tilgung und | S116: aus Verkauf des | T116: (Verkaufswert)
P117: zuwachs | Q117: zu-/abfluss | R117: kumu. Cash Flow | S117: Objektes | T117: des Objektes
Q118: nach Steuern | R118: nach Steuern | S118: über die Jahre | T118: über die Jahre
P119: 5 Jahre | Q119: ='Cash & Assets'!AI56 -> 63252.508 | R119: ='Cash & Assets'!AL56 -> 101114.09 | S119: ='Cash & Assets'!AS53 -> 24327.152 | T119: ='Cash & Assets'!AQ53 -> 1071413.1
P120: 10 Jahre | Q120: ='Cash & Assets'!AI57 -> 126011.21 | R120: ='Cash & Assets'!AL57 -> 184606.22 | S120: ='Cash & Assets'!AS54 -> 140288.35 | T120: ='Cash & Assets'!AQ54 -> 1103882.1
P121: 15 Jahre | Q121: ='Cash & Assets'!AI58 -> 179865.97 | R121: ='Cash & Assets'!AL58 -> 238460.98 | S121: ='Cash & Assets'!AS55 -> 227708.27 | T121: ='Cash & Assets'!AQ55 -> 1137447.3
P122: 20 Jahre | Q122: ='Cash & Assets'!AI59 -> 257617.06 | R122: ='Cash & Assets'!AL59 -> 316212.07 | S122: ='Cash & Assets'!AS56 -> 340162.36 | T122: ='Cash & Assets'!AQ56 -> 1172150.3
P123: 25 Jahre | Q123: ='Cash & Assets'!AI60 -> 362902.89 | R123: ='Cash & Assets'!AL60 -> 421497.89 | S123: ='Cash & Assets'!AS57 -> 481332.57 | T123: ='Cash & Assets'!AQ57 -> 1208034.7
P124: 30 Jahre | Q124: ='Cash & Assets'!AI61 -> 488661.89 | R124: ='Cash & Assets'!AL61 -> 547256.89 | S124: ='Cash & Assets'!AS58 -> 644202.75 | T124: ='Cash & Assets'!AQ58 -> 1245145.9

Sheet ChangeLog
A1: Version | B1: Changes | C1: by | D1: Date | E1: Filename
A14: V 5.0 | B14: Release für Publikation in Controllingportal.de | C14: Klaus F. Odenwälder | D14: 45989 | E14: 2025_11_28 Wie muss ein Immobilien-Investor mit Förderkredit rechnen.xlsx bzw. Wie muss ein Immobilien-Investor mit Förderkredit rechnen.xlsx
A15: V 4.7 | B15: im Blatt "Parameter" Eingabenfür Förderkredit eingebaut und Zellen mit Labels aufgeführt, im Blatt: Cash & Assets Spalten für Förderkredit eingschoben, Übersichtlichkeit verbessert mit mehr leeren Spalten, Kennzahlenblatt (Restschulden) modiziert, | C15: Klaus F. Odenwälder | D15: 45985 | E15: 2025_11_24 Wie muss ein Immobilien-Investor mit Förderkredit rechnen Beta_Version.xlsx
A16: V4.6 | B16: Im Blatt "Hinweise" Erläuterungen korrigiert und mit Tabelle zur jährlichen (Anfangs-)Tilgung ergänzt, im Blatt "Parameter" Zellen mit Labels aufgeführt Cash & Asstes mit leeren Spalten zur Verbesserung des Layouts | C16: Klaus F. Odenwälder | D16: 45982 | E16: 2025_11_21 Wie muss ein Immobilien-Investor.xlsx bzw. Wie muss ein Immobilien-Investor rechnen.xlsx
A17: V4.5 | B17: Kalkualtion der Rendite in Spalte AA korrigiert = Yn +Jn Berechnung des "Mittel-Überschusses bei hypoth. Verkauf" (Blatt Kennzahlen, Zelle N16) und Link auf Download-Website korrigiert | C17: Klaus F. Odenwälder | D17: 45812 | E17: 2025_04_06 Wie muss ein Immobilien-Investor.xlsx bzw. Wie muss ein Immobilien-Investor rechnen.xlsx
A18: V4.4 | B18: Fehlerkorrektur: Instandhaltungskosten am Anfang (Parameter-Blatt Zeile 14) weden jetzt in der Cash&Assets-Kalkulation reflektiert (in Zelle L8) | C18: Klaus F. Odenwälder | D18: 45684 | E18: 2025_01_27 Wie muss ein Immobilien-Investor.xlsx bzw. Wie muss ein Immobilien-Investor rechnen.xlsx
A19: V4.3 | B19: Im Parameter-Blatt (Zelle B55 ) sowie im Hinweise-Blatt (ab Zeile 92) Info. zur anfänglichen jährlichen Tilgung eingefügt! | C19: Klaus F. Odenwälder | D19: 45469 | E19: 2024_06_26 Wie muss ein Immobilien-Investor.xlsx bzw. Wie muss ein Immobilien-Investor rechnen.xlsx
A20: V4.2 | B20: Die vergessene Korrektur des Rechenfehler für den Gewinn aus V+V beseitigt, die Formel ist jetzt so, wie in der Beschreibung der Kalkulationslogik (dort war die Logik korrekt) | C20: Klaus F. Odenwälder | D20: 45417 | E20: 2024_05_05 Wie muss ein Immobilien-Investor.xlsx bzw. Wie muss ein Immobilien-Investor rechnen.xlsx
A21: V4.1 | B21: AfA als "Negativer Wert" in "Cash & Asset Blatt" eingeführt, da AfA Aufwand (aber keine Mittelabfluss) bedeutet Erläuterung zur Berechungen (Kalkulationslogik) des zu versteuernden Gewinn im Blatt "Cash & Assets" hinzugefügt | C21: Klaus F. Odenwälder | D21: 45406 | E21: 2024_04_24 Wie muss ein Immobilien-Investor.xlsx bzw. Wie muss ein Immobilien-Investor rechnen.xlsx
A22: V4.0 | B22: Neu eingeführt: Diverse (anpassungsfähige) AfA Varianten in der AfA Tabelle (zum Anpassen) Spalte für Sonder-AfA Spalte für Sondertilgung | C22: Klaus F. Odenwälder | D22: 45396 | E22: 2024_04_14 Wie muss ein Immobilien-Investor mit Degr AfA rechnen.xlsx
A23: V3.3 | B23: AfA Varianten eingeführt: Linear mit 2% oder 3% und Degresiiv Linear mit 5 % in den ersten sechs Jahren und danach 3 % p.a. | C23: Klaus F. Odenwälder | D23: 45392 | E23: 2024_04_10 Wie-muss-ein-Immobilien_Investor mit Degr AfA rechnen.xlsx
A24: V3.2 | B24: Zusammenführung der Blätter "Cash" und "Assets" in ein Blatt "Cash & Assets" Eigenkapialrendite-Rechnung angefügt | C24: Klaus F. Odenwälder | D24: 44418 | E24: 2021-08-10 Wie muss ein Immobilien-Investor rechnen.xlsx
A25: V3.1 | B25: Korrektur der AFA-Basis: Erwerbsnebenkosten werden anteilig auf das Gebäude angerechnet und aktiviert und über die Lebendauer abgeschrieben. | C25: Klaus F. Odenwälder | D25: 44416 | E25: 2021-08-08 Wie muss ein Immobilien-Investor rechnen.xlsx
... A28: V1.0 | B28: Diverse Updates & Verfeinerungen | C28: Klaus F. Odenwälder | D28: 40465 | E28: 2010-10-14 Was werfen Immobilien ab.xlsx
A29: V1.0 | B29: Inital Version | C29: Klaus F. Odenwälder | D29: vor 2000
